Workbook
Name ____WO1: #REF!
Name ___WO1: #REF!
Name __A23: #N/A
Name __A23: [0]!__A23
Name __ASI87: #N/A
Name __ASI87: [0]!__ASI87
Name __d1: #N/A
Name __d1: [0]!__d1
Name __d6: #N/A
Name __d6: [0]!__d6
Name __D7: #N/A
Name __D7: [0]!__D7
Name __d8: #N/A
Name __d8: [0]!__d8
Name __DAS4556: #N/A
Name __DAS4556: [0]!__DAS4556
Name __ddf1: #N/A
Name __ddf1: [0]!__ddf1
Name __DDS12: #N/A
Name __DDS12: [0]!__DDS12
Name __ds1: #N/A
Name __ds1: [0]!__ds1
Name __DSS1: #N/A
Name __DSS1: [0]!__DSS1
Name __f31: #N/A
Name __f31: [0]!__f31
Name __F4: #N/A
Name __F4: [0]!__F4
Name __F5: #N/A
Name __F5: [0]!__F5
Name __fa213: #N/A
Name __fa213: [0]!__fa213
Name __far45: #N/A
Name __far45: [0]!__far45
Name __fd543: #N/A
Name __fd543: [0]!__fd543
Name __fdd32: #N/A
Name __fdd32: [0]!__fdd32
Name __FDD456: #N/A
Name __FDD456: [0]!__FDD456
Name __FGD4321: #N/A
Name __FGD4321: [0]!__FGD4321
Name __FSD4: #N/A
Name __FSD4: [0]!__FSD4
Name __fsf6: #N/A
Name __fsf6: [0]!__fsf6
Name __G4: #N/A
Name __G4: [0]!__G4
Name __G5: #N/A
Name __G5: [0]!__G5
Name __g7: #N/A
Name __g7: [0]!__g7
Name __g987: #N/A
Name __g987: [0]!__g987
Name __GF54: #N/A
Name __GF54: [0]!__GF54
Name __GFF54: #N/A
Name __GFF54: [0]!__GFF54
Name __ghg655: #N/A
Name __ghg655: [0]!__ghg655

Sheet LP
B2: LISTA DE PRECIOS DYNADRILL ECUADOR C.A.
B4: CODIGO | C4: DESCRIPCION DE ITEMS | D4: UNIDAD | E4: Nuevo Precio | F4: Tipo
B5: 2.2.15 Servicios de Estimulación y Limpieza de Pozos
A6: 1 | B6: SB3201 | C6: Viaje por unidad de bombeo para estimulación | D6: km | E6: 3.15 | F6: Servicio
A7: =A6+1 -> 2 | B7: SB3205 | C7: Unidad de bombeo para estimulación por hora adicional o fracción | D7: hr | E7: 26.78 | F7: Servicio
A8: =A7+1 -> 3 | B8: SB3206 | C8: Mezcla de materiales suministrados por la contratista. | D8: gls | E8: 0.09 | F8: Servicio
A9: =A8+1 -> 4 | B9: SB3207 | C9: Mezcla de materiales no suministrados por la contratista. | D9: gls | E9: 0.25 | F9: Servicio
A10: =A9+1 -> 5 | B10: SB3208 | C10: Bombeo de ácido primeros 2.000 galones | D10: gls | E10: 0.33 | F10: Servicio
A11: =A10+1 -> 6 | B11: SB3209 | C11: Bombeo de ácido de 2.001 a 4.000 galones | D11: gls | E11: 0.33 | F11: Servicio
A12: =A11+1 -> 7 | B12: SB3210 | C12: Bombeo de ácido de 4001 galones en adelante | D12: gls | E12: 0.33 | F12: Servicio
A13: =A12+1 -> 8 | B13: SB3211 | C13: Bombeo de fluidos no corrosivos primeros 2.000 galones | D13: gls | E13: 0.25 | F13: Servicio
A14: =A13+1 -> 9 | B14: SB3212 | C14: Bombeo de fluidos no corrosivos de 2.001 a 4.000 galones | D14: gls | E14: 0.25 | F14: Servicio
A15: =A14+1 -> 10 | B15: SB3213 | C15: Bombeo de Fluidos no corrosivos de 4001 galones en adelante | D15: gls | E15: 0.25 | F15: Servicio
A16: =A15+1 -> 11 | B16: SB3214 | C16: Tanque para tratamiento de 100 barriles | D16: unidad | E16: 257.1 | F16: Servicio
A17: =A16+1 -> 12 | B17: SB3215 | C17: Tanques para ácido o solventes de 1.000 a 1500 galones | D17: unidad | E17: 398.49 | F17: Servicio
A18: =A17+1 -> 13 | B18: SB3216 | C18: Cargo por monitoreo standard de presión, caudal y densidad | D18: unidad | E18: 373.8 | F18: Servicio
... A178: =A177+1 -> 173 | B178: Q21151 | C178: Arena Sand Jet Perforación Micro arena | D178: lbs | E178: 1.32 | F178: Material
B179: 2.2.14 Servicios de Completacion de Pozos
A180: =A178+1 -> 174 | B180: PCK 50001 | C180: HYDRAULIC SET RETRIEVABLE PACKER 5" x 2 3/8'' EUE Box-Pin CASING 5'' WEIGHT 18-21 lbs/FT | D180: unidad | E180: 9544.5 | F180: Material
A181: =A180+1 -> 175 | B181: PCK 50002 | C181: HYDRAULIC SET RETRIEVABLE PACKER 7" x 2 7/8'' EUE Box-Pin CASING 7'' WEIGHT 26-29 lbs/FT | D181: unidad | E181: 10092.95 | F181: Material
A182: =A181+1 -> 176 | B182: PCK 50003 | C182: HYDRAULIC SET RETRIEVABLE PACKER 7" x 3 1/2'' EUE Box-Pin CASING 7'' WEIGHT 26-29 lbs/FT | D182: unidad | E182: 11570.33 | F182: Material
A183: =A182+1 -> 177 | B183: PCK 50004 | C183: HYDRAULIC SET RETRIEVABLE PACKER 9 5/8" x 3 1/2'' EUE Box-Pin CASING 9 5/8'' WEIGHT 43.5-53.5 lbs/FT | D183: unidad | E183: 20084.99 | F183: Material
A184: =A183+1 -> 178 | B184: PCK 50005 | C184: RETRIEVABLE HYDRAULIC PACKER STRING 7" x 2 7/8'' EUE Box-Pin CASING 7'' WEIGHT 26-29 lbs/FT | D184: unidad | E184: 9729.69 | F184: Material
A185: =A184+1 -> 179 | B185: PCK 50006 | C185: RETRIEVABLE HYDRAULIC PACKER STRING 7" x 3 1/2'' EUE Box-Pin CASING 7'' WEIGHT 26-29 lbs/FT | D185: unidad | E185: 11570.33 | F185: Material
A186: =A185+1 -> 180 | B186: PCK 50007 | C186: RETRIEVABLE HYDRAULIC PACKER STRING 9 5/8" x 3 1/2'' EUE Box-Pin CASING 9 5/8'' WEIGHT 47-53.5 lbs/FT | D186: unidad | E186: 19358.45 | F186: Material
A187: =A186+1 -> 181 | B187: PCK 50008 | C187: DOUBLE GRIP RETRIEVABLE PACKER MODEL R 5" x 2 3/8'' EUE Box-Pin CASING 5'' WEIGHT 15-18 lbs/FT | D187: unidad | E187: 7726.77 | F187: Material
A188: =A187+1 -> 182 | B188: PCK 50009 | C188: DOUBLE GRIP RETRIEVABLE PACKER MODEL R 7" x 2 7/8'' EUE Box-Pin CASING 7'' WEIGHT 26-29 lbs/FT | D188: unidad | E188: 10599.34 | F188: Material
A189: =A188+1 -> 183 | B189: PCK 50010 | C189: DOUBLE GRIP RETRIEVABLE PACKER MODEL R 7" x 3 1/2'' EUE Box-Pin CASING 7'' WEIGHT 26-29 lbs/FT | D189: unidad | E189: 11570.33 | F189: Material
A190: =A189+1 -> 184 | B190: PCK 50011 | C190: DOUBLE GRIP RETRIEVABLE PACKER MODEL R 9 5/8" x 3 1/2'' EUE Box-Pin CASING 9 5/8'' WEIGHT 47''-53.5 lbs/FT | D190: unidad | E190: 16831.75 | F190: Material
A191: =A190+1 -> 185 | B191: PCK 50012 | C191: MODEL TST-1 MECHANICAL SET PACKER 5" x 2 3/8'' EUE Box-Pin CASING 5'' WEIGHT 18-21 lbs/FT | D191: unidad | E191: 7381.56 | F191: Material
A192: =A191+1 -> 186 | B192: PCK 50013 | C192: MODEL TST-1 MECHANICAL SET PACKER 7" x 2 7/8'' EUE Box-Pin CASING 7'' WEIGHT 26-32 lbs/FT | D192: unidad | E192: 10583.23 | F192: Material
... A354: =A353+1 -> 348 | B354: SFS6292 | C354: TOP PACKER SETTING TOOL ALL SIZE | D354: Corrida | E354: 3975.66 | F354: Servicio
B355: 2.1.30. Servicios de Taponamiento de cemento para desvíos o abandonos de pozo
A356: =A354+1 -> 349 | B356: SC2301 | C356: Viaje unidad de bombeo, para el servicio de cementación forzada | D356: km | E356: 3.15 | F356: Servicio
A357: =A356+1 -> 350 | B357: SC2304 | C357: Primeras 4 horas o fracción, cargo básico por unidad de bombeo alta presión | D357: unidad | E357: 2363.58 | F357: Servicio
A358: =A357+1 -> 351 | B358: SC2305 | C358: Cada hora adicional o fracción de trabajo, por unidad de bombeo alta presión | D358: hr | E358: 125.8 | F358: Servicio
A359: =A358+1 -> 352 | B359: SC2306 | C359: Cargo por profundidad, hasta 11.000 pies. | D359: Pie | E359: 0.07 | F359: Servicio
A360: =A359+1 -> 353 | B360: SC2307 | C360: Cargo por profundidad, de 11.001 hasta 14.000 Pies | D360: Pie | E360: 0.15 | F360: Servicio
A361: =A360+1 -> 354 | B361: SC2308 | C361: Batch mixer de 100 barriles por trabajo | D361: unidad | E361: 689.19 | F361: Servicio
A362: =A361+1 -> 355 | B362: SC2309 | C362: Adaptador de 2 3/8", 2 7/8", 3 1/2", 4 1/2" para cementación forzada | D362: unidad | E362: 44.86 | F362: Servicio
A363: =A362+1 -> 356 | B363: SC2310 | C363: Cargo por monitoreo standard de presión, caudal y densidad para lechadas | D363: unidad | E363: 365.71 | F363: Servicio
A364: =A363+1 -> 357 | B364: SC2311 | C364: Registrador de presión tipo Martín Decker, por trabajo | D364: unidad | E364: 89.7 | F364: Servicio
A365: =A364+1 -> 358 | B365: SC2312 | C365: Setting Tool para cementacion forzada, por trabajo | D365: unidad | E365: 177.77 | F365: Servicio
A366: =A365+1 -> 359 | B366: SC2313 | C366: Stinger cementación forzada, por trabajo | D366: unidad | E366: 99.06 | F366: Servicio
A367: =A366+1 -> 360 | B367: SC2314 | C367: Manifold de alta presión, por trabajo | D367: unidad | E367: 112.13 | F367: Servicio
A368: =A367+1 -> 361 | B368: SC2315 | C368: Mov. Cemento y adit.:Ton-Km,( incluido manipuleo) | D368: Tn - km | E368: 1.19 | F368: Servicio
... A507: =A506+1 -> 500 | B507: Q21089 | C507: DYCoastalSpot - Concentrado para píldora despegante de Pega Diferencial | D507: gls | E507: 22.98 | F507: Material
B508: 2.1.31. Servicios de Limpieza de Revestidor
A509: =A507+1 -> 501 | B509: SH1100 | C509: SARTA DE LIMPIEZA PARA CASING 5'' - 5 1/2'' Incuye (casing scraper, cepillo , magneto , canasta), personal tecnico, redress. | D509: Corrida | E509: 4823.35 | F509: Servicio
A510: =A509+1 -> 502 | B510: SH1101 | C510: SARTA DE LIMPIEZA PARA CASING 7'' Incuye (casing scraper, cepillo , magneto , canasta), personal tecnico, redress. | D510: Corrida | E510: 4262.52 | F510: Servicio
A511: =A510+1 -> 503 | B511: SH1102 | C511: SARTA DE LIMPIEZA PARA CASING 9 5/8'' Incuye (casing scraper, cepillo , magneto , canasta), personal tecnico, redress. | D511: Corrida | E511: 4696 | F511: Servicio
A512: =A511+1 -> 504 | B512: SH1103 | C512: SARTAS DE LIMPIEZA EN TANDEM PARA CASING 7" Y 9-5/8" Incluye (casing scraper, cepillo , magneto , canasta), personal tecnico, redress. | D512: Corrida | E512: 5205.79 | F512: Servicio
A513: =A512+1 -> 505 | B513: SH1104 | C513: SARTAS DE LIMPIEZA EN TANDEM PARA CASING 5" Y 7" Incluye (casing scraper, cepillo , magneto , canasta), personal tecnico, redress. | D513: Corrida | E513: 7478.39 | F513: Servicio
A514: =A513+1 -> 506 | B514: SH1105 | C514: SCRAPER PARA CASING 4 1/2-5 1/2" | D514: Corrida | E514: 2101.92 | F514: Servicio
A515: =A514+1 -> 507 | B515: SH1106 | C515: SCRAPER PARA CASING 7" | D515: Corrida | E515: 2690.46 | F515: Servicio
A516: =A515+1 -> 508 | B516: SH1107 | C516: SCRAPER PARA CASING 9 5/8" | D516: Corrida | E516: 3194.91 | F516: Servicio
A517: =A516+1 -> 509 | B517: SH1108 | C517: CANASTA PARA CASING 4 1/2-5 1/2" | D517: Corrida | E517: 2101.92 | F517: Servicio
A518: =A517+1 -> 510 | B518: SH1109 | C518: CANASTA PARA CASING 7" | D518: Corrida | E518: 2690.46 | F518: Servicio
A519: =A518+1 -> 511 | B519: SH1110 | C519: CANASTA PARA CASING 9 5/8" | D519: Corrida | E519: 3194.91 | F519: Servicio
A520: =A519+1 -> 512 | B520: SCR5201 | C520: ROTATING JET CLEAN SYSTEM TOOL 2.5¨ - 2 3/8¨ EUE BOX UP | D520: Corrida | E520: 4160.05 | F520: Servicio
A521: =A520+1 -> 513 | B521: SCR5202 | C521: SAND JET PERFORATING TOOL - 3.500¨ - 2 3/8¨ EUE BOX x PIN - PRIMERAS 8 HORAS | D521: unidad | E521: 1466.08 | F521: Servicio
... A526: =A525+1 -> 518 | B526: SCR5207 | C526: Asistente de Operaciones para fluidos de completacion dia o fraccion | D526: día | E526: 109.31 | F526: Servicio
B527: 2.1.07. Servicios de Pesca
A528: =A526+1 -> 519 | B528: SH1001 | C528: Operador de Thru Tubing dia o fraccion dia o fraccion | D528: día | E528: 330.54 | F528: Servicio
A529: =A528+1 -> 520 | B529: SH1006 | C529: Tapon Inflable de 1-11/16" HASTA 2-1/8'' OD | D529: unidad | E529: 19396.19 | F529: Material
A530: =A529+1 -> 521 | B530: SH1007 | C530: SARTA DE (MHA): O.D 1-11/16" | D530: Corrida | E530: 2232.1 | F530: Servicio
A531: =A530+1 -> 522 | B531: SH1008 | C531: SARTA DE (MHA): O.D 1-1/2" | D531: Corrida | E531: 2232.1 | F531: Servicio
A532: =A531+1 -> 523 | B532: SH1009 | C532: SARTA DE (MHA): O.D 2-1/8" | D532: Corrida | E532: 2309.07 | F532: Servicio
A533: =A532+1 -> 524 | B533: SH1010 | C533: SARTA DE (MHA): O.D 2-7/8" | D533: Corrida | E533: 2309.07 | F533: Servicio
A534: =A533+1 -> 525 | B534: SH1011 | C534: SARTA DE (MHA) PARA BAJAR TAPON RECUPERABLE 1-11/16" HASTA 2-1/8'' OD | D534: Corrida | E534: 3345.84 | F534: Servicio
A535: =A534+1 -> 526 | B535: SH1012 | C535: SARTA DE GS SPEAR HIDRAULICO: O.D 1-3/4" | D535: Corrida | E535: 9467.19 | F535: Servicio
A536: =A535+1 -> 527 | B536: SH1013 | C536: SARTA DE PESCANTE DE GUAYA TIPO CAIMAN | D536: Corrida | E536: 5879.12 | F536: Servicio
A537: =A536+1 -> 528 | B537: SH1014 | C537: SARTA DE PESCANTE DE GUAYA TIPO ARPON | D537: Corrida | E537: 5879.12 | F537: Servicio
A538: =A537+1 -> 529 | B538: SH1015 | C538: SARTA DE JDC HIDRAULICO: 2'' HASTA 3 1/2'' OD | D538: Corrida | E538: 9467.19 | F538: Servicio
A539: =A538+1 -> 530 | B539: SH1016 | C539: SARTA DE OVERSHOT-CONTINUO MECANICO: HASTA 3 1/2 O.D | D539: Corrida | E539: 6452.71 | F539: Servicio
A540: =A539+1 -> 531 | B540: SH1017 | C540: SARTA DE OVERSHOT HIDRAULICO : HASTA 3 1/2 OD | D540: Corrida | E540: 7121.88 | F540: Servicio
... A813: =A812+1 -> 804 | B813: SFS6293 | C813: Tubing Bailer Assembly (incluye flapper) - hasta 5-3/4" OD - Cargo por Corrida | D813: Corrida | E813: 2241.64 | F813: Servicio
B814: 2.2.11. Servicios de Reacondicionamiento
A815: =+A813+1 -> 805 | B815: SCR5001 | C815: SUPERVISOR PARA COMPLETACIONES, REMEDIACION dia o fraccion | D815: día | E815: 437.23 | F815: Servicio
A816: =+A815+1 -> 806 | B816: SCR5002 | C816: Movilizacion unidades livianas para transporte de personal | D816: km | E816: 2.66 | F816: Servicio
A817: =+A816+1 -> 807 | B817: SCR5003 | C817: Movilizacion unidades pesadas para transporte de herramientas | D817: km | E817: 3.15 | F817: Servicio
A818: =+A817+1 -> 808 | B818: SCR5004 | C818: MODEL "DYNBKR" MECHANICAL SETTING TOOL PARA COMPLETACION. TODOS LOS DIAMETROS | D818: Corrida | E818: 1976.9 | F818: Servicio
A819: =+A818+1 -> 809 | B819: SCR5005 | C819: MODEL "DYNBKR" STINGER CARGO | D819: Corrida | E819: 2142.42 | F819: Servicio
A820: =+A819+1 -> 810 | B820: SCR5006 | C820: MODEL "FURY 20" HYDRAULIC SETTING TOOL FOR PACKERS, CR, CIBP, ETC. TODOS LOS DIAMETROS | D820: Corrida | E820: 2356.67 | F820: Servicio
A821: =+A820+1 -> 811 | B821: SCR5007 | C821: ACT WIRELINE ADAPTER KIT FOR WIRELINE SET TOOLS. TODOS LOS DIAMETROS | D821: Corrida | E821: 1285.46 | F821: Servicio
A822: =+A821+1 -> 812 | B822: SCR5008 | C822: MODEL TST-1 O R MECHANICAL SET PACKER 9 5/8" x 3 1/2'' EUE Box-Pin CASING 9 5/8'' WEIGHT 43.5-53.5 lbs/FT CARGO HASTA ASENTAMIENTO | D822: Corrida | E822: 2999.38 | F822: Servicio
A823: =+A822+1 -> 813 | B823: SCR5009 | C823: MODEL TST-1 O R MECHANICAL SET PACKER 9 5/8" x 3 1/2'' EUE Box-Pin CASING 9 5/8'' WEIGHT 43.5-53.5 lbs/FT CARGO POR HORA DESPUES DE ASENTAMIENTO | D823: hr | E823: 42.86 | F823: Servicio
A824: =+A823+1 -> 814 | B824: SCR5010 | C824: MODEL TST-1 O R MECHANICAL SET PACKER 7" x 3 1/2'' O 2 7/8'' EUE Box-Pin CASING 7'' WEIGHT 26-32lbs/FT CARGO HASTA ASENTAMIENTO | D824: Corrida | E824: 1912.87 | F824: Servicio
A825: =+A824+1 -> 815 | B825: SCR5011 | C825: MODEL TST-1 O R MECHANICAL SET PACKER 7" x 3 1/2'' O 2 7/8'' EUE Box-Pin CASING 7'' WEIGHT 26-32lbs/FT CARGO POR HORA DESPUES DE ASENTAMIENTO | D825: hr | E825: 27.98 | F825: Servicio
A826: =+A825+1 -> 816 | B826: SCR5012 | C826: MODEL TST-1 O R MECHANICAL SET PACKER 5" x 2 3/8'' EUE Box-Pin CASING 5'' WEIGHT 18-21 lbs/FT CARGO HASTA ASENTAMIENTO | D826: Corrida | E826: 2313.81 | F826: Servicio
A827: =+A826+1 -> 817 | B827: SCR5013 | C827: MODEL TST-1 O R MECHANICAL SET PACKER 5" x 2 3/8'' EUE Box-Pin CASING 5'' WEIGHT 18-21 lbs/FT CARGO POR HORA DESPUES DE ASENTAMIENTO | D827: hr | E827: 25.72 | F827: Servicio
... A876: =+A875+1 -> 866 | B876: SRPN7217 | C876: Reparacion Mayor Equalizing Chcek Valve 2,75" | D876: unidad | E876: 1408.27 | F876: Servicio
B877: 2.2.07. Servicios de Control de Pozos
A878: =+A876+1 -> 867 | B878: SFC33001 | C878: Movilización unidad de bombeo para fluidos de completación | D878: km | E878: 3.15 | F878: Servicio
A879: =A878+1 -> 868 | B879: SFC33003 | C879: Cargo básico bomba para preparación fluidos de completación, primeras 4 horas o fracción | D879: unidad | E879: 3420.87 | F879: Servicio
A880: =A879+1 -> 869 | B880: SFC33004 | C880: Unidad bombeo para preparación fluidos de completación por hora adicional | D880: hr | E880: 183.05 | F880: Servicio
A881: =A880+1 -> 870 | B881: SFC33005 | C881: Mezcla de materiales suministrados por Dynadrill | D881: gls | E881: 0.34 | F881: Servicio
A882: =A881+1 -> 871 | B882: SFC33006 | C882: Mezcla de materiales no suministrados por Dynadrill | D882: gls | E882: 0.42 | F882: Servicio
A883: =A882+1 -> 872 | B883: SFC33007 | C883: Servicio de Bombeo de ácido primeros 2500 galones | D883: gls | E883: 0.34 | F883: Servicio
A884: =A883+1 -> 873 | B884: SFC33008 | C884: Servicio de Bombeo de fluidos corrosivos de 2500 gls hasta 4200 gls | D884: gls | E884: 0.41 | F884: Servicio
...

Sheet BD
C1: 000 | D1: N/A
C2: 001 | D2: QUITO | E2: BLOQUE UIO | F2: BLOQUE UIO | BN2: B01 | BO2: BLOQUE 01 | BR2: AMILCAR DIAZ ESPINEL | BS2: BLOQUE 58 | BV2: CCDC-028 | BW2: Company Man | BZ2: César Saeteros | CA2: 0602033219 | CD2: Ing. Alejandro Sagal | CE2: 1714829056 | CF2: Coordinador de Producción | CG2: ORION
C3: 002 | D3: INDILLANA | E3: BLOQUE 15 | F3: BLOQUE 15 | BN3: B02 | BO3: BLOQUE 02 | BR3: AGUARICO | BS3: BLOQUE 57 | BV3: CCDC-036 | BW3: Ingeniero de Operaciones | BZ3: José Luis Sáenz | CA3: 1716475585 | CD3: Ing. Alex Fabara | CE3: 1720193281 | CF3: Company man | CG3: SLB
C4: 002 | D4: CONCORDIA | E4: BLOQUE 15 | BN4: B03 | BO4: BLOQUE 03 | BR4: AMISTAD | BS4: BLOQUE 06 | BV4: CCDC-039 | BW4: Supervisor de Producción | BZ4: Carlos Poveda | CA4: 1600165292 | CD4: Ing. Alex Hernández | CE4: 0602958449 | CF4: Ingeniero de Operaciones | CG4: PEC
C5: 002 | D5: ITAYA | E5: BLOQUE 15 | BN5: B05 | BO5: BLOQUE 05 | BR5: ANACONDA | BS5: BLOQUE 61 | BV5: CCDC-040 | BW5: Intendente de Producción | BZ5: Giordano Ferretti | CA5: 1758720617 | CD5: Ing. Alfredo Obando | CE5: 0703887703 | CF5: Company man | CG5: ORION
C6: 002 | D6: JIVINO | E6: BLOQUE 15 | BN6: B06 | BO6: BLOQUE 06 | BR6: ANGEL NORTE | BS6: BLOQUE 15 | BV6: CCDC-042 | BW6: Coordinador de Producción | BZ6: Manolo Salazar | CA6: 1712815180 | CD6: Ing. Andrea Sampedro | CE6: 1718317207 | CF6: Ingeniera de Operaciones | CG6: PEC
C7: 002 | D7: LAGUNA | E7: BLOQUE 15 | BN7: B07 | BO7: BLOQUE 07 | BR7: ANURA | BS7: BLOQUE 61 | BV7: CCDC-051 | BW7: Superintendente de campo | BZ7: Javier Guevara | CA7: 1713206843 | CD7: Ing. Andrés Aldas | CE7: 1712764271 | CF7: Company man | CG7: WAYRA
C8: 002 | D8: NAPO | E8: BLOQUE 15 | BN8: B10 | BO8: BLOQUE 10 | BR8: APAIKA | BS8: BLOQUE 31 | BV8: CCDC-052 | BZ8: Jeferson Lemache | CA8: 0604107870 | CD8: Ing. Andrés Cisneros | CE8: 1717527483 | CF8: Company man | CG8: PEC
C9: 003 | D9: LIMONCOCHA | E9: BLOQUE 15 | BN9: B11 | BO9: BLOQUE 11 | BR9: ARAZA | BS9: BLOQUE 57 | BV9: CCDC-066 | BZ9: July Ana Masache | CA9: 1500239395 | CD9: Ing. Andrés Paredes | CE9: 0401359328 | CF9: Ingeniero de Operaciones | CG9: PEC
C10: 004 | D10: EDEN YUTURI | E10: BLOQUE 12 | F10: BLOQUE 12 | BN10: B12 | BO10: BLOQUE 12 | BR10: ARMADILLO | BS10: BLOQUE 55 | BV10: CCDC-069 | BZ10: Hermes Fabián Páez | CA10: 0502223423 | CD10: Ing. Aníbal Aguilar | CE10: 1719861369 | CF10: Ingeniero de Operaciones | CG10: PEC
C11: 005 | D11: EXPLORACION | F11: BLOQUE EXPLORACION | BN11: B14 | BO11: BLOQUE 14 | BR11: ATACAPI | BS11: BLOQUE 57 | BV11: CSSFD-01 | BZ11: Luis Auquilla | CA11: 0602471153 | CD11: Ing. Anita Guillen | CE11: 0604271320 | CF11: Ingeniera de Operaciones | CG11: PEC
C12: 006 | D12: OLEODUCTO | F12: BLOQUE 12 | BN12: B15 | BO12: BLOQUE 15 | BR12: AUCA | BS12: BLOQUE 61 | BV12: DRILLCOTEC-020 | BZ12: Alberto Tipanluisa | CA12: 1712736485 | CD12: Ing. Arturo Barreiro | CE12: 0914096235 | CF12: Company man | CG12: PEC
C13: 007 | D13: YANAQUINCHA | E13: BLOQUE 15 | F13: BLOQUE 15 | BN13: B16 | BO13: BLOQUE 16 | BR13: AUCA SUR | BS13: BLOQUE 61 | BV13: DT-10 | BZ13: Andrés Pazmiño | CA13: 2100447412 | CD13: Ing. Byron Caiza | CE13: 1722720677 | CF13: Supervisor de Producción | CG13: PEC
C14: 007 | D14: PACAY | E14: BLOQUE 15 | BN14: B17 | BO14: BLOQUE 17 | BR14: BLANCA | BS14: BLOQUE 58 | BV14: DYGOIL-20 | BZ14: Antonio Moreira | CA14: 2100176045 | CD14: Ing. Byron Calero | CE14: 1716336514 | CF14: Company man | CG14: PEC
C15: 007 | D15: ANGEL NORTE | E15: BLOQUE 15 | BN15: B18 | BO15: BLOQUE 18 | BR15: BOA | BS15: BLOQUE 61 | BV15: DYGOIL-30 | BZ15: Sebastian Jimenez | CA15: 1710457837 | CD15: Ing. Carlos Jímenez | CE15: 1002189858 | CF15: Coordinador de Producción | CG15: ORION
C16: 008 | D16: PAKA SUR | E16: BLOQUE 15 | BN16: B20 | BO16: BLOQUE 20 | BR16: CALUMENIA | BS16: BLOQUE 58 | BV16: E&A 12 | BZ16: Carlos Coloma | CA16: 1600153413 | CD16: Ing. Carlos Pineda | CE16: 1710691005 | CF16: Company man | CG16: PNTR
C17: 009 | D17: PAKA NORTE | E17: BLOQUE 15 | BN17: B21 | BO17: BLOQUE 21 | BR17: CEDROS SUR | BS17: BLOQUE 15 | BV17: ELEFANTE AZUL 01 | BZ17: Clinger Yanez | CA17: 1711689370 | CD17: Ing. Carlos Ramírez | CE17: 1804490504 | CF17: Company man | CG17: PEC
C18: 010 | D18: PAÑACOCHA | E18: BLOQUE 12 | F18: BLOQUE 12 | BN18: B22 | BO18: BLOQUE 22 | BR18: CHONTA ESTE | BS18: BLOQUE 61 | BV18: FASTDRILLING-11 | BZ18: Darwin Piña | CA18: 2100549100 | CD18: Ing. Carlos Robalino | CE18: 0502078546 | CF18: Company man | CG18: PEC
C19: 011 | D19: YANKUNT | E19: BLOQUE 15 | F19: BLOQUE 15 | BN19: B28 | BO19: BLOQUE 28 | BR19: COBRA | BS19: BLOQUE 57 | BV19: GEOPETSA-03 | BZ19: Edison Falla | CA19: 1500756067 | CD19: Ing. Carlos Salazar | CE19: 0918279597 | CF19: Supervisor de Producción | CG19: PEC
C20: 011 | D20: PALMAR | E20: BLOQUE 15 | F20: BLOQUE 15 | BN20: B31 | BO20: BLOQUE 31 | BR20: COCA | BS20: BLOQUE 07 | BV20: GEOPETSA-04 | BZ20: Fabián Hernández | CA20: 0603049586 | CD20: Ing. Carlos Toapanta | CE20: 1719353102 | CF20: Company man | CG20: PBELL
C21: 011 | D21: PALMERAS | E21: BLOQUE 15 | F21: BLOQUE 15 | BN21: B43 | BO21: BLOQUE 43 | BR21: CONCORDIA | BS21: BLOQUE 15 | BV21: GEOPETSA-05 | BZ21: Iván Granda | CA21: 1712100138 | CD21: Ing. Carlos Zurita | CE21: 1717192098 | CF21: Ingeniero de Producción | CG21: ANDES
C22: 011 | D22: TUNTIAK | E22: BLOQUE 15 | F22: BLOQUE 15 | BN22: B44 | BO22: BLOQUE 44 | BR22: CONDORAZO | BS22: BLOQUE 57 | BV22: GEOPETSA-06 | BZ22: Omar Bravo | CA22: 1713306601 | CD22: Ing. César Chávez | CE22: 1500568371 | CF22: Company man | CG22: PEC
C23: 011 | D23: TUICH | E23: BLOQUE 15 | F23: BLOQUE 15 | BN23: B45 | BO23: BLOQUE 45 | BR23: CONGA | BS23: BLOQUE 61 | BV23: GEOPETSA-07 | BZ23: Wilber Cárdenas | CA23: 2100116827 | CD23: Ing. César Venegas | CE23: 0927632240 | CF23: Company man | CG23: PEC
C24: 012 | D24: DUMBIQUE | E24: BLOQUE 12 | F24: BLOQUE 12 | BN24: B46 | BO24: BLOQUE 46 | BR24: CONONACO | BS24: BLOQUE 61 | BV24: HILONG 15 | CD24: César Maza | CE24: 1712787991 | CF24: Supervisor de Producción | CG24: PEC
C25: 013 | D25: PAÑAYACU | E25: BLOQUE 15 | F25: BLOQUE 15 | BN25: B47 | BO25: BLOQUE 47 | BR25: CULEBRA | BS25: BLOQUE 61 | BV25: HILONG 28 | CD25: Ing. Cristian Tierra | CE25: 0603607250 | CF25: Supervisor de Producción | CG25: PEC
C26: 040 | D26: OGE SECTORIAL | E26: BLOQUE 40 | F26: BLOQUE 40 | BN26: B48 | BO26: BLOQUE 48 | BR26: CUYABENO | BS26: BLOQUE 58 | BV26: NABORS 794 | CD26: Ing. Cristina Castillo | CE26: 1500536949 | CF26: Ingeniera de Operaciones | CG26: PEC
C27: 015 | D27: CEDROS SUR | E27: BLOQUE 15 | F27: BLOQUE 15 | BN27: B49 | BO27: BLOQUE 49 | BR27: DRAGO | BS27: BLOQUE 57 | BV27: NABORS 814 | CD27: Ing. Daniel Balseca | CE27: 1803906450 | CF27: Company man | CG27: PEC
C28: 015 | D28: QUINDE | E28: BLOQUE 15 | F28: BLOQUE 15 | BN28: B50 | BO28: BLOQUE 50 | BR28: DRAGO NORTE | BS28: BLOQUE 57 | BV28: NABORS 815 | CD28: Ing. Daniel Constante | CE28: 1803789351 | CF28: Ingeniero de Operaciones | CG28: PEC
C29: 016 | D29: DUMBIQUE SUR | E29: BLOQUE 12 | F29: BLOQUE 12 | BN29: B51 | BO29: BLOQUE 51 | BR29: DRAGO ESTE | BS29: BLOQUE 57 | BV29: ORD-902 | CD29: Ing. Daniel Cuenca | CE29: 1714303490 | CF29: Ingeniero de Operaciones | CG29: PEC
C30: 017 | D30: YANAHURCO | E30: BLOQUE 12 | BN30: B52 | BO30: BLOQUE 52 | BR30: DUMBIQUE | BS30: BLOQUE 12 | BV30: ORD-903 | CD30: Ing. Daniel Esparza | CE30: 1712734787 | CF30: Company man | CG30: PEC
C31: 018 | D31: TUMALI ESTE | E31: BLOQUE 12 | BN31: B53 | BO31: BLOQUE 53 | BR31: DUMBIQUE SUR | BS31: BLOQUE 12 | BV31: PETREX-20 | CD31: Ing. Daniel Pabón | CE31: 1002912838 | CF31: Company man | CG31: PEC
C32: 030 | D32: PALO AZUL | E32: BLOQUE 18 | F32: BLOQUE 18 | G32: ZONA OESTE | BN32: B54 | BO32: BLOQUE 54 | BR32: EDEN YUTURI | BS32: BLOQUE 12 | BV32: PETROTECH 04 | CD32: Ing. Daniel Orellana | CE32: 1719240481 | CF32: Supervisor de Producción | CG32: PEC
C33: 031 | D33: PATA | E33: BLOQUE 18 | BN33: B55 | BO33: BLOQUE 55 | BR33: FRONTERA | BS33: BLOQUE 57 | BV33: PW-150 | CD33: Ing. Danny Cuenca | CE33: 1713148003 | CF33: Superintendente de campo | CG33: GOIL
C34: 050 | D34: YURALPA | E34: BLOQUE 21 | F34: BLOQUE 21 | BN34: B56 | BO34: BLOQUE 56 | BR34: GACELA | BS34: BLOQUE 07 | BV34: SAXON 32 | CD34: Ing. Danny Enríquez | CE34: 0400956785 | CF34: Company man | CG34: PEC
C35: 055 | D35: ARMADILLO | E35: BLOQUE 55 | F35: BLOQUE 55 | BN35: B57 | BO35: BLOQUE 57 | BR35: GASODUCTO | BS35: BLOQUE 06 | BV35: SAXON 34 | CD35: Ing. Darwin Mejía | CE35: 1307572782 | CF35: Supervisor de Producción | CG35: PEC
C36: 060 | D36: COCA | E36: BLOQUE 07 | F36: BLOQUE 07 | BN36: B58 | BO36: BLOQUE 58 | BR36: GUANTA | BS36: BLOQUE 56 | BV36: SAXON 47 | CD36: Ing. David Jaque | CE36: 1715419329 | CF36: Ingeniero de Operaciones | CG36: PEC
C37: 061 | D37: PAYAMINO | E37: BLOQUE 07 | BN37: B59 | BO37: BLOQUE 59 | BR37: GUSTAVO GALINDO | BS37: BLOQUE 01 | BV37: SAXON 56 | CD37: Ing. Diana Aviles | CE37: 0927252460 | CF37: Ingeniera de Operaciones | CG37: PEC
C38: 062 | D38: GACELA | E38: BLOQUE 07 | BN38: B60 | BO38: BLOQUE 60 | BR38: HUAICO | BS38: BLOQUE 58 | BV38: SAXON-55 | CD38: Ing. Diego Cunalata | CE38: 1803879210 | CF38: Company man | CG38: PEC
C39: 063 | D39: LOBO | E39: BLOQUE 07 | BN39: B61 | BO39: BLOQUE 61 | BR39: INDILLANA | BS39: BLOQUE 15 | BV39: SAXON-56 | CD39: Ing. Diego Herrera | CE39: 0401095351 | CF39: Ingeniero de Operaciones UIO | CG39: PEC
C40: 064 | D40: MONO | E40: BLOQUE 07 | BN40: B62 | BO40: BLOQUE 62 | BR40: ITAYA | BS40: BLOQUE 15 | BV40: SINOPEC 119 | CD40: Ing. Diego Molina | CE40: 1713267878 | CF40: Company man | CG40: PEC
C41: 065 | D41: OSO | E41: BLOQUE 07 | BN41: B64 | BO41: BLOQUE 64 | BR41: JIVINO | BS41: BLOQUE 15 | BV41: SINOPEC 127 | CD41: Ing. Diego Rodriguez | CE41: 1803395050 | CF41: Ingeniero de Operaciones | CG41: PEC
C42: 070 | D42: TIPUTINI | E42: BLOQUE 43 | F42: BLOQUE 43 | G42: ZONA ESTE | BN42: B65 | BO42: BLOQUE 65 | BR42: LAGO AGRIO | BS42: BLOQUE 56 | BV42: SINOPEC 156 | CD42: Ing. Diego Vásquez | CE42: 1309494431 | CF42: Company man | CG42: PEC
C43: 071 | D43: TAMBOCOCHA | E43: BLOQUE 43 | BN43: B66 | BO43: BLOQUE 66 | BR43: LAGUNA | BS43: BLOQUE 15 | BV43: SINOPEC 168 | CD43: Edgar Larreategui | CE43: 0200971935 | CF43: Supervisor de Producción | CG43: PEC
C44: 080 | D44: APAIKA | E44: BLOQUE 31 | F44: BLOQUE 31 | BN44: B67 | BO44: BLOQUE 67 | BR44: LIMONCOCHA | BS44: BLOQUE 15 | BV44: SINOPEC 169 | CD44: Tnlgo. Edgar Calvache | CE44: 1717515439 | CF44: Supervisor de Producción | CG44: PEC
C45: 080 | D45: NENKE | E45: BLOQUE 31 | BN45: B70 | BO45: BLOQUE 70 | BR45: LOBO | BS45: BLOQUE 07 | BV45: SINOPEC 183 | CD45: Ing. Edison Medrano | CE45: 1711988079 | CF45: Company man | CG45: PEC
B46: LAGO AGRIO | C46: 100 | D46: GUANTA | E46: BLOQUE 56 | F46: BLOQUE 56 | G46: ZONA NORTE | BN46: B75 | BO46: BLOQUE 75 | BR46: MONO | BS46: BLOQUE 07 | BV46: SINOPEC 185 | CD46: Ing. Edison Andrés Mendez | CE46: 723028690 | CF46: Company man | CG46: PEC
C47: 101 | D47: LAGO AGRIO | E47: BLOQUE 56 | BN47: B76 | BO47: BLOQUE 76 | BR47: NAPO | BS47: BLOQUE 15 | BV47: SINOPEC 191 | CD47: Ing. Edisson Calderón | CE47: 0401120225 | CF47: Company man | CG47: PEC
C48: 102 | D48: PARAHUACO | E48: BLOQUE 56 | BN48: B79 | BO48: BLOQUE 79 | BR48: NENKE | BS48: BLOQUE 31 | BV48: SINOPEC 219 | CD48: Ing. Edisson Lozada | CE48: 1803430196 | CF48: Company man | CG48: PEC
B49: SHUSHUFINDI | C49: 110 | D49: SHUSHUFINDI | E49: BLOQUE 57 | F49: BLOQUE 57 | BN49: B80 | BO49: BLOQUE 80 | BR49: OGE SECTORIAL | BS49: BLOQUE 40 | BV49: SINOPEC 220 | CD49: Ing. Edwin Muñoz | CE49: 1400285068 | CF49: Company man | CG49: PEC
C50: 111 | D50: AGUARICO | E50: BLOQUE 57 | BN50: B83 | BO50: BLOQUE 83 | BR50: OSO | BS50: BLOQUE 07 | BV50: SINOPEC 248 | CD50: Ing. Edwin Saavedra | CE50: 1103388813 | CF50: Company man | CG50: PEC
C51: 112 | D51: DRAGO | E51: BLOQUE 57 | BN51: B86 | BO51: BLOQUE 86 | BR51: PACAY | BS51: BLOQUE 15 | BV51: SINOPEC 907 | CD51: Ing. Efren De la Cueva | CE51: 1713781746 | CF51: Company man | CG51: PEC
C52: 113 | D52: CONDORAZO | E52: BLOQUE 57 | BN52: B92 | BO52: BLOQUE 92 | BR52: PACAYUCU | BS52: BLOQUE 57 | BV52: SINOPEC 932 | CD52: Ing. Efrén Yugsi | CE52: 1711155992 | CF52: Ingeniero de Operaciones UIO | CG52: PEC
C53: 114 | D53: COBRA | E53: BLOQUE 57 | BN53: B93 | BO53: BLOQUE 93 | BR53: PACOA | BS53: BLOQUE 01 | BV53: SINOPEC-219 | CD53: Ing. Elvis González | CE53: 0919402230 | CF53: Company man | CG53: PEC
B54: LIBERTADOR | C54: 120 | D54: ATACAPI | E54: BLOQUE 57 | BR54: PAKA NORTE | BS54: BLOQUE 15 | BV54: SINOPEC-904 | CD54: Ing. Enrique Espín | CE54: 1708720527 | CF54: Ingeniero de Operaciones | CG54: PEC
C55: 121 | D55: FRONTERA | E55: BLOQUE 57 | BR55: PAKA SUR | BS55: BLOQUE 15 | BV55: SINOPEC-905 | CD55: Ing. Erick López | CE55: 1204068595 | CF55: Ingeniero de Operaciones | CG55: PEC
C56: 122 | D56: TAPI | E56: BLOQUE 57 | BR56: PALMAR OESTE | BS56: BLOQUE 15 | BV56: SLR-401 | CD56: Ing. Fausto Villamar | CE56: 0924420334 | CF56: Supervisor de Producción | CG56: PEC
C57: 123 | D57: TETETE | E57: BLOQUE 57 | BR57: PALMERAS | BS57: BLOQUE 15 | BV57: SLR-402 | CD57: Ing. Fausto Sánchez | CE57: 1803855509 | CF57: Ingeniero de Operaciones | CG57: PEC
C58: 124 | D58: SHUSHUQUI | E58: BLOQUE 57 | BR58: PALMERAS NORTE | BS58: BLOQUE 15 | BV58: TRIBOILGAS-001 | CD58: Ing. Fernando Bonilla | CE58: 1720557084 | CF58: Company man | CG58: PEC
C59: 125 | D59: SHUARA | E59: BLOQUE 57 | BR59: PALO AZUL | BS59: BLOQUE 18 | BV59: TRIBOILGAS-004 | CD59: Ing. Fidel Moreira | CE59: 1308119633 | CF59: Ingeniero de Operaciones | CG59: PEC
C60: 125 | D60: PACAYUCU | E60: BLOQUE 57 | BR60: PAÑACOCHA | BS60: BLOQUE 12 | BV60: TRIBOILGAS-008 | CD60: Ing. Franklin Cajamarca | CE60: 1721049946 | CF60: Company man | CG60: WAYRA
C61: 126 | D61: PICHINCHA | E61: BLOQUE 57 | BR61: PAÑAYACU | BS61: BLOQUE 15 | BV61: TRIBOILGAS-101 | CD61: Ing. Freddy Iñiga | CE61: 0912537941 | CF61: Company man | CG61: PEC
C62: 127 | D62: SECOYA | E62: BLOQUE 57 | BR62: PARAHUACO | BS62: BLOQUE 56 | BV62: TRIBOILGAS-102 | CD62: Ing. Freddy Pantoja | CE62: 0400999793 | CF62: Ingeniero de Operaciones | CG62: PEC
C63: 128 | D63: ARAZA | E63: BLOQUE 57 | BR63: PATA | BS63: BLOQUE 18 | BV63: TRIBOILGAS-103 | CD63: Ing. Gabriel López | CE63: 1713019105 | CF63: Supervisor de Producción | CG63: PEC
B64: CUYABENO | C64: 140 | D64: VHR (Víctor Hugo Ruales) | E64: BLOQUE 58 | F64: BLOQUE 58 | BR64: PAYAMINO | BS64: BLOQUE 07 | BV64: TRIBOILGAS-104 | CD64: Ing. Gabriel Muñoz | CE64: 1003493549 | CF64: Company man | CG64: PEC
C65: 141 | D65: SANSAHUARI | E65: BLOQUE 58 | BR65: PICHINCHA | BS65: BLOQUE 57 | BV65: TRIBOILGAS-105 | CD65: Ing. Gabriela Llorenty | CE65: 0925462756 | CF65: Ingeniera de Operaciones | CG65: PEC
C66: 142 | D66: CUYABENO | E66: BLOQUE 58 | BR66: PITALALA | BS66: BLOQUE 61 | BV66: TRIBOILGAS-106 | CD66: Ing. Geovanni Alemán | CE66: 1718517475 | CF66: Company man | CG66: ORION
C67: 143 | D67: BLANCA | E67: BLOQUE 58 | BR67: PUCUNA | BS67: BLOQUE 44 | BV67: TRIBOILGAS-107 | CD67: Ing. Germán Morillo | CE67: 1713622387 | CF67: Ingeniero de Operaciones | CG67: PEC
C68: 144 | D68: TIPISHCA | E68: BLOQUE 58 | BR68: QUINDE | BS68: BLOQUE 15 | BV68: TRIBOILGAS-201 | CD68: Ing. Giovanni Herrera | CE68: 1710013861 | CF68: Company man | CG68: PEC
C69: 144 | D69: HUAICO | E69: BLOQUE 58 | BR69: RUMIYACU | BS69: BLOQUE 61 | BV69: TRIBOILGAS-203 | CD69: Ing. Guillermo Remache | CE69: 0802365379 | CF69: Ingeniero de Operaciones | CG69: PEC
C70: 145 | D70: AED (Amilcar Espinel Díaz) | E70: BLOQUE 58 | BR70: SACHA | BS70: BLOQUE 60 | BV70: TRIBOILGAS-204 | CD70: Ing. Hector Bravo | CE70: 1310798275 | CF70: Ingeniero de Operaciones | CG70: PEC
C71: 146 | D71: VINITA | E71: BLOQUE 59 | F71: BLOQUE 59 | BR71: SAMI | BS71: BLOQUE 61 | BV71: TUSCANY-104 | CD71: Ing. Henry Raza | CE71: 1500634371 | CF71: Ingeniero de Operaciones | CG71: PEC
B72: PUCUNA | C72: 160 | D72: PUCUNA | E72: BLOQUE 44 | F72: BLOQUE 44 | G72: ZONA OESTE | BR72: SANSAHUARI | BS72: BLOQUE 58 | BV72: TUSCANY-105 | CD72: Ing. Henry Ariadel | CE72: 0704415306 | CF72: Ingeniero de Operaciones | CG72: PEC
B73: AUCA | C73: 161 | D73: AUCA | E73: BLOQUE 61 | F73: BLOQUE 61 | BR73: SECOYA | BS73: BLOQUE 57 | BV73: TUSCANY-111 | CD73: Ing. Hernán Aguilar | CE73: 1003933270 | CF73: Company man | CG73: PNTR
C74: 161 | D74: CONGA | E74: BLOQUE 61 | BR74: SHUARA | BS74: BLOQUE 57 | BV74: TUSCANY-119 | CD74: Ing. Holger Oleas | CE74: 1712806403 | CF74: Ingeniero de Operaciones | CG74: PEC
C75: 162 | D75: CONONACO | E75: BLOQUE 61 | BR75: SHUSHUFINDI | BS75: BLOQUE 57 | BV75: RIGLESS | CD75: Ing. Ismael Labanda | CE75: 0502276306 | CF75: Ingeniero de Operaciones | CG75: PEC
C76: 163 | D76: CULEBRA | E76: BLOQUE 61 | BR76: SHUSHUQUI | BS76: BLOQUE 57 | BV76: RIGLESS - TRABAJOS EN SUPERFICIE | CD76: Ing. Jaime Garrido | CE76: 1002424537 | CF76: Supervisor de Producción | CG76: PEC
C77: 164 | D77: YULEBRA | E77: BLOQUE 61 | BR77: TAMBOCOCHA | BS77: BLOQUE 43 | CD77: Ing. Javier Mejia | CE77: 0401397815 | CF77: Company man | CG77: PCR
C78: 165 | D78: RUMIYACU | E78: BLOQUE 61 | BR78: TANGAY | CD78: Ing. Jefferson Alvarez | CE78: 1717046922 | CF78: Ingeniero de Operaciones | CG78: PEC
C79: 166 | D79: YUCA | E79: BLOQUE 61 | BR79: TANGAY ESTE | CD79: Ing. Jefferson Proaño | CE79: 1204499535 | CF79: Ingeniero de Operaciones | CG79: PEC
C80: 167 | D80: ANACONDA | E80: BLOQUE 61 | BR80: TAPI | BS80: BLOQUE 57 | CD80: Ing. Jhonny Grefa | CE80: 1500789035 | CF80: Ingeniero de Operaciones | CG80: PEC
C81: 168 | D81: CHONTA ESTE | E81: BLOQUE 61 | BR81: TETETE | BS81: BLOQUE 57 | CD81: Ing. Jhonny Noguera | CE81: 1706378724 | CF81: Company man | CG81: PEC
C82: 169 | D82: PITALALA | E82: BLOQUE 61 | BR82: TIPISHCA | BS82: BLOQUE 58 | CD82: Ing. Jimmy Vélez | CE82: 1309450789 | CF82: Company man | CG82: PNTR
C83: 170 | D83: SAMI | E83: BLOQUE 61 | BR83: TIPUTINI | BS83: BLOQUE 43 | CD83: Ing. Jorge Corella | CE83: 0705110450 | CF83: Company man | CG83: PEC
C84: 170 | D84: ANURA | E84: BLOQUE 61 | BR84: TORTUGA | BS84: BLOQUE 61 | CD84: Ing. Jorge Cruz | CE84: 1205792391 | CF84: Ingeniero de Operaciones | CG84: PEC
C85: 171 | D85: TORTUGA | E85: BLOQUE 61 | BR85: TUICH | BS85: BLOQUE 15 | CD85: Ing. Jorge Hurtado | CE85: 1714023288 | CF85: Ingeniero de Operaciones | CG85: PEC
C86: 172 | D86: BOA | E86: BLOQUE 61 | BR86: TUMALI | BS86: BLOQUE 12 | CD86: Ing. Jorge Jaramillo | CE86: 1709220139 | CF86: Company man | CG86: PEC
C87: 172 | D87: BOA | E87: BLOQUE 61 | BR87: TUMALI ESTE | BS87: BLOQUE 15 | CD87: Ing. Jorge Pozo | CE87: 0401021431 | CF87: Ingeniero de Operaciones | CG87: PEC
B88: SACHA | C88: 300 | D88: SACHA | E88: BLOQUE 60 | F88: BLOQUE 60 | G88: ZONA NORTE | BR88: TUMALI SURESTE | BS88: BLOQUE 12 | CD88: Ing. José Luis Velásquez | CE88: 1714498118 | CF88: Company man | CG88: PEC
B89: LITORAL | C89: 200 | D89: PACOA | E89: BLOQUE 01 | F89: BLOQUE 01 | G89: ZONA LITORAL | BR89: TUNTIAK | BS89: BLOQUE 15 | CD89: Ing. José Velásquez | CE89: 1706378724 | CF89: Company man | CG89: PEC
C90: 201 | D90: GUSTAVO GALINDO | E90: BLOQUE 01 | BR90: VICTOR HUGO RUALES | BS90: BLOQUE 58 | CD90: Ing. Juan Molina | CE90: 1713556551 | CF90: Company man | CG90: PEC
B91: GAS NATURAL | C91: 500 | D91: AMISTAD | E91: BLOQUE 06 | F91: BLOQUE 06 | G91: ZONA MACHALA | BR91: VINITA | BS91: BLOQUE 59 | CD91: Ing. Julio Quinga | CE91: 1803840121 | CF91: Ingeniero de Operaciones | CG91: PEC
C92: 520 | D92: GASODUCTO | E92: BLOQUE 06 | BR92: YANAHURCO | BS92: BLOQUE 12 | CD92: Ing. Karen Escobar | CE92: 1721753935 | CF92: Company man | CG92: PEC
B93: BLOQUE | C93: 001 | D93: QUITO | F93: PETROPROAMAZONAS EP | BR93: YANAQUINCHA NORTE | BS93: BLOQUE 15 | CD93: Ing. Kléber Armijos | CE93: 1712801255 | CF93: Company man | CG93: PEC
C94: 007 | D94: BLOQUE 07 | BR94: YANAQUINCHA ESTE | BS94: BLOQUE 15 | CD94: Ing. Leonardo Pazmiño | CE94: 1802930089 | CF94: Company man | CG94: PEC
C95: 012 | D95: BLOQUE 12 | BR95: YANAQUINCHA OESTE | BS95: BLOQUE 15 | CD95: Ing. Luis Alabuela | CE95: 1713884763 | CF95: Ingeniero de Operaciones | CG95: PEC
C96: 015 | D96: BLOQUE 15 | BR96: YANAQUINCHA SUR | BS96: BLOQUE 15 | CD96: Ing. Luis Santiago Freire | CE96: 1803305026 | CF96: Ingeniero de Operaciones | CG96: PEC
C97: 018 | D97: BLOQUE 18 | BR97: YANAQUINCHA OESTE | BS97: BLOQUE 15 | CD97: Ing. Luis Murgueytio | CE97: 0802651794 | CF97: Company man | CG97: PEC
C98: 021 | D98: BLOQUE 21 | BR98: YUCA | BS98: BLOQUE 61 | CD98: Ing. Luis Ordoñez | CE98: 1716515364 | CF98: Company man | CG98: PNTR
C99: 031 | D99: BLOQUE 31 | BR99: YULEBRA | BS99: BLOQUE 61 | CD99: Ing. Marcelo Venegas | CF99: Ingeniero de Producción | CG99: ANDES
C100: 006 | D100: BLOQUE 06 | F100: ANTERIOR EP PEC | BR100: YURALPA | BS100: BLOQUE 21 | CD100: Ing. Marco Castillo | CE100: 1717978173 | CF100: Ingeniero de Operaciones | CG100: PEC
...

Sheet Clientes
A1: Nombre Fiscal | B1: Identificación
A2: ADRIALPETRO PETROLEUM SERVICES S.A. | B2: 1791406281001
A3: CONDOR SERVICIOS PETROLEROS CONSEPETRO S.A. | B3: 1792832209001
A4: CONSORCIO PETROLERO NACIONAL | B4: 1792723256001
A5: CONSORCIO PETROSUD PETRORIVA | B5: 1791749146001
A6: CONSORCIO PETROLERO PALANDA -YUCA SUR | B6: 1792260787001
A7: CONSORCIO SHUSHUFINDI S.A. | B7: 1792352363001
A8: CPVEN SERVICIOS PETROLEROS LTD | B8: 1791818415001
A9: EMPRESA PUBLICA DE HIDROCARBUROS DEL ECUADOR EP PETROECUADOR | B9: 1768153530001
A10: ENAP SIPETROL S.A. - ENAP SIPEC | B10: 1791239245001
A11: GENTE OIL ECUADOR PTE. LTD. | B11: 1792452929001
A12: GYRODATA ECUADOR L.L.C. | B12: 1792274966001
... A25: XAVIER VASQUEZ | B25: 0603431453

Sheet OTQ
C3: ORDEN DE TRABAJO
C5: RESUMEN DE COSTOS
A7: CONTRATISTA: DYNADRILL ECUADOR C.A. | D7: No. : | E7: 892-OPR-GLCH-022-UIO-2026 | H7: Página 1 de 1
A8: CONTRATO 2025201 - SERVICIOS EVENTUALES BAJO LLAMADA DE APOYO A LAS OPERACIONES, SERVICIOS DE ESTIMULACIÓN Y LIMPIEZA DE POZOS, ACTIVIDADES RELACIONADAS CON LA PRODUCCIÓN, COMPLETACION INICIAL DE POZOS, RENTA DE HERRAMIENTAS DE REACONDICIONAMIENTO/COMPLETACIÓN Y PROVISIÓN DE INSUMOS Y MATERIALES PARA ACTIVIDADES DE CEMENTACIÓN Y TRATAMIENTO DE FLUIDOS ÚNICAMENTE PARA LA PRESTACIÓN DE SERVICIOS RELACIONADOS AL OBJETO DEL CONTRATO EN LOS CAMPOS DE EP PETROECUADOR INCLUIDO BLOQUE 6 (OFFSHORE) | D8: FECHA: | E8: 46233
A9: Descripción del Requerimiento o de la Orden de Trabajo | G9: NOTA: No inicie actividades sin información previa
A10: SERVICIO: | B10: =CONCATENATE([6]TICKET!E17,"/",[6]TICKET!E15,"/",[6]TICKET!E16) -> BOMBEO SISTEMA SOLVENTE ACIDO/GCLH-022/RIGLESS
A11: Las tarifas serán las del Contrato 2025201 las mismas que serán incluidas en la presente hoja de costos estimados
A12: CODIGO | B12: SERVICIOS REQUERIDOS | E12: UNIDAD | F12: TARIFA UNITARIA | G12: CANTIDAD | H12: TOTAL
A13: =+TICKET!D19 -> SFC33001 | B13: =IF(A13="","",IF(ISERROR(VLOOKUP(A13,'[7]LISTA DE PRECIOS'!B$7:E$1788,2,0)),"",VLOOKUP(A13,'[7]LISTA DE PRECIOS'!B$7:E$1788,2,0))) -> Movilización unidad de bombeo para fluidos de completación | E13: =IF(A13="","",IF(ISERROR(VLOOKUP(A13,'[7]LISTA DE PRECIOS'!B$7:E$1788,3,0)),"",VLOOKUP(A13,'[7]LISTA DE PRECIOS'!B$7:E$1788,3,0))) -> km | F13: =IF(A13="","",IF(ISERROR(VLOOKUP(A13,'[7]LISTA DE PRECIOS'!B$7:E$1788,4,0)),"",VLOOKUP(A13,'[7]LISTA DE PRECIOS'!B$7:E$1788,4,0))) -> 3.15 | G13: =+TICKET!E19 -> 33.6 | H13: =+F13*G13 -> 105.84
A14: =+TICKET!D20 -> SB3240 | B14: =IF(A14="","",IF(ISERROR(VLOOKUP(A14,'[7]LISTA DE PRECIOS'!B$7:E$1788,2,0)),"",VLOOKUP(A14,'[7]LISTA DE PRECIOS'!B$7:E$1788,2,0))) -> Cargo básico, primeras 4 horas o fracción de bombeo unidad de estimulación (700 HP) | E14: =IF(A14="","",IF(ISERROR(VLOOKUP(A14,'[7]LISTA DE PRECIOS'!B$7:E$1788,3,0)),"",VLOOKUP(A14,'[7]LISTA DE PRECIOS'!B$7:E$1788,3,0))) -> unidad | F14: =IF(A14="","",IF(ISERROR(VLOOKUP(A14,'[7]LISTA DE PRECIOS'!B$7:E$1788,4,0)),"",VLOOKUP(A14,'[7]LISTA DE PRECIOS'!B$7:E$1788,4,0))) -> 3180.54 | G14: =+TICKET!E20 -> 1 | H14: =+F14*G14 -> 3180.54
A15: =+TICKET!D21 -> SFC33024 | B15: =IF(A15="","",IF(ISERROR(VLOOKUP(A15,'[7]LISTA DE PRECIOS'!B$7:E$1788,2,0)),"",VLOOKUP(A15,'[7]LISTA DE PRECIOS'!B$7:E$1788,2,0))) -> Tanque para ácido o solvente de 6500 galones, por trabajo | E15: =IF(A15="","",IF(ISERROR(VLOOKUP(A15,'[7]LISTA DE PRECIOS'!B$7:E$1788,3,0)),"",VLOOKUP(A15,'[7]LISTA DE PRECIOS'!B$7:E$1788,3,0))) -> unidad | F15: =IF(A15="","",IF(ISERROR(VLOOKUP(A15,'[7]LISTA DE PRECIOS'!B$7:E$1788,4,0)),"",VLOOKUP(A15,'[7]LISTA DE PRECIOS'!B$7:E$1788,4,0))) -> 773.77 | G15: =+TICKET!E21 -> 1 | H15: =+F15*G15 -> 773.77
A16: =+TICKET!D22 -> SFC33032 | B16: =IF(A16="","",IF(ISERROR(VLOOKUP(A16,'[7]LISTA DE PRECIOS'!B$7:E$1788,2,0)),"",VLOOKUP(A16,'[7]LISTA DE PRECIOS'!B$7:E$1788,2,0))) -> Supervisor Senior para fluidos de completación dia o fraccion | E16: =IF(A16="","",IF(ISERROR(VLOOKUP(A16,'[7]LISTA DE PRECIOS'!B$7:E$1788,3,0)),"",VLOOKUP(A16,'[7]LISTA DE PRECIOS'!B$7:E$1788,3,0))) -> día | F16: =IF(A16="","",IF(ISERROR(VLOOKUP(A16,'[7]LISTA DE PRECIOS'!B$7:E$1788,4,0)),"",VLOOKUP(A16,'[7]LISTA DE PRECIOS'!B$7:E$1788,4,0))) -> 833.41 | G16: =+TICKET!E22 -> 1 | H16: =+F16*G16 -> 833.41
A17: =+TICKET!D23 -> SFC33017 | B17: =IF(A17="","",IF(ISERROR(VLOOKUP(A17,'[7]LISTA DE PRECIOS'!B$7:E$1788,2,0)),"",VLOOKUP(A17,'[7]LISTA DE PRECIOS'!B$7:E$1788,2,0))) -> Operador para fluidos de completación dia o fraccion | E17: =IF(A17="","",IF(ISERROR(VLOOKUP(A17,'[7]LISTA DE PRECIOS'!B$7:E$1788,3,0)),"",VLOOKUP(A17,'[7]LISTA DE PRECIOS'!B$7:E$1788,3,0))) -> día | F17: =IF(A17="","",IF(ISERROR(VLOOKUP(A17,'[7]LISTA DE PRECIOS'!B$7:E$1788,4,0)),"",VLOOKUP(A17,'[7]LISTA DE PRECIOS'!B$7:E$1788,4,0))) -> 349.78 | G17: =+TICKET!E23 -> 1 | H17: =+F17*G17 -> 349.78
A18: =+TICKET!D24 -> SFC33017 | B18: =IF(A18="","",IF(ISERROR(VLOOKUP(A18,'[7]LISTA DE PRECIOS'!B$7:E$1788,2,0)),"",VLOOKUP(A18,'[7]LISTA DE PRECIOS'!B$7:E$1788,2,0))) -> Operador para fluidos de completación dia o fraccion | E18: =IF(A18="","",IF(ISERROR(VLOOKUP(A18,'[7]LISTA DE PRECIOS'!B$7:E$1788,3,0)),"",VLOOKUP(A18,'[7]LISTA DE PRECIOS'!B$7:E$1788,3,0))) -> día | F18: =IF(A18="","",IF(ISERROR(VLOOKUP(A18,'[7]LISTA DE PRECIOS'!B$7:E$1788,4,0)),"",VLOOKUP(A18,'[7]LISTA DE PRECIOS'!B$7:E$1788,4,0))) -> 349.78 | G18: =+TICKET!E24 -> 1 | H18: =+F18*G18 -> 349.78
A19: =+TICKET!D25 -> SFC33014 | B19: =IF(A19="","",IF(ISERROR(VLOOKUP(A19,'[7]LISTA DE PRECIOS'!B$7:E$1788,2,0)),"",VLOOKUP(A19,'[7]LISTA DE PRECIOS'!B$7:E$1788,2,0))) -> Tarifa de monitoreo en unidad de bombeo Presión, Densidad, Caudal, Volumen | E19: =IF(A19="","",IF(ISERROR(VLOOKUP(A19,'[7]LISTA DE PRECIOS'!B$7:E$1788,3,0)),"",VLOOKUP(A19,'[7]LISTA DE PRECIOS'!B$7:E$1788,3,0))) -> día | F19: =IF(A19="","",IF(ISERROR(VLOOKUP(A19,'[7]LISTA DE PRECIOS'!B$7:E$1788,4,0)),"",VLOOKUP(A19,'[7]LISTA DE PRECIOS'!B$7:E$1788,4,0))) -> 373.74 | G19: =+TICKET!E25 -> 1 | H19: =+F19*G19 -> 373.74
A20: =+TICKET!D26 -> SFC33011 | B20: =IF(A20="","",IF(ISERROR(VLOOKUP(A20,'[7]LISTA DE PRECIOS'!B$7:E$1788,2,0)),"",VLOOKUP(A20,'[7]LISTA DE PRECIOS'!B$7:E$1788,2,0))) -> Bombeo de fluidos no corrosivos de 2500 hasta 4200 galones | E20: =IF(A20="","",IF(ISERROR(VLOOKUP(A20,'[7]LISTA DE PRECIOS'!B$7:E$1788,3,0)),"",VLOOKUP(A20,'[7]LISTA DE PRECIOS'!B$7:E$1788,3,0))) -> gls | F20: =IF(A20="","",IF(ISERROR(VLOOKUP(A20,'[7]LISTA DE PRECIOS'!B$7:E$1788,4,0)),"",VLOOKUP(A20,'[7]LISTA DE PRECIOS'!B$7:E$1788,4,0))) -> 0.38 | G20: =+TICKET!E26 -> 4200 | H20: =+F20*G20 -> 1596
A21: =+TICKET!D27 -> SFC33007 | B21: =IF(A21="","",IF(ISERROR(VLOOKUP(A21,'[7]LISTA DE PRECIOS'!B$7:E$1788,2,0)),"",VLOOKUP(A21,'[7]LISTA DE PRECIOS'!B$7:E$1788,2,0))) -> Servicio de Bombeo de ácido primeros 2500 galones | E21: =IF(A21="","",IF(ISERROR(VLOOKUP(A21,'[7]LISTA DE PRECIOS'!B$7:E$1788,3,0)),"",VLOOKUP(A21,'[7]LISTA DE PRECIOS'!B$7:E$1788,3,0))) -> gls | F21: =IF(A21="","",IF(ISERROR(VLOOKUP(A21,'[7]LISTA DE PRECIOS'!B$7:E$1788,4,0)),"",VLOOKUP(A21,'[7]LISTA DE PRECIOS'!B$7:E$1788,4,0))) -> 0.34 | G21: =+TICKET!E27 -> 840 | H21: =+F21*G21 -> 285.6
A22: =+TICKET!D28 -> SFC33027 | B22: =IF(A22="","",IF(ISERROR(VLOOKUP(A22,'[7]LISTA DE PRECIOS'!B$7:E$1788,2,0)),"",VLOOKUP(A22,'[7]LISTA DE PRECIOS'!B$7:E$1788,2,0))) -> Movilización de equipo adicional, unidades pesadas. | E22: =IF(A22="","",IF(ISERROR(VLOOKUP(A22,'[7]LISTA DE PRECIOS'!B$7:E$1788,3,0)),"",VLOOKUP(A22,'[7]LISTA DE PRECIOS'!B$7:E$1788,3,0))) -> km | F22: =IF(A22="","",IF(ISERROR(VLOOKUP(A22,'[7]LISTA DE PRECIOS'!B$7:E$1788,4,0)),"",VLOOKUP(A22,'[7]LISTA DE PRECIOS'!B$7:E$1788,4,0))) -> 3.15 | G22: =+TICKET!E28 -> 33.6 | H22: =+F22*G22 -> 105.84
A23: =+TICKET!D29 -> SFC33027 | B23: =IF(A23="","",IF(ISERROR(VLOOKUP(A23,'[7]LISTA DE PRECIOS'!B$7:E$1788,2,0)),"",VLOOKUP(A23,'[7]LISTA DE PRECIOS'!B$7:E$1788,2,0))) -> Movilización de equipo adicional, unidades pesadas. | E23: =IF(A23="","",IF(ISERROR(VLOOKUP(A23,'[7]LISTA DE PRECIOS'!B$7:E$1788,3,0)),"",VLOOKUP(A23,'[7]LISTA DE PRECIOS'!B$7:E$1788,3,0))) -> km | F23: =IF(A23="","",IF(ISERROR(VLOOKUP(A23,'[7]LISTA DE PRECIOS'!B$7:E$1788,4,0)),"",VLOOKUP(A23,'[7]LISTA DE PRECIOS'!B$7:E$1788,4,0))) -> 3.15 | G23: =+TICKET!E29 -> 33.6 | H23: =+F23*G23 -> 105.84
A24: =+TICKET!D30 -> SFC33026 | B24: =IF(A24="","",IF(ISERROR(VLOOKUP(A24,'[7]LISTA DE PRECIOS'!B$7:E$1788,2,0)),"",VLOOKUP(A24,'[7]LISTA DE PRECIOS'!B$7:E$1788,2,0))) -> Movilización unidades livianas para personal | E24: =IF(A24="","",IF(ISERROR(VLOOKUP(A24,'[7]LISTA DE PRECIOS'!B$7:E$1788,3,0)),"",VLOOKUP(A24,'[7]LISTA DE PRECIOS'!B$7:E$1788,3,0))) -> km | F24: =IF(A24="","",IF(ISERROR(VLOOKUP(A24,'[7]LISTA DE PRECIOS'!B$7:E$1788,4,0)),"",VLOOKUP(A24,'[7]LISTA DE PRECIOS'!B$7:E$1788,4,0))) -> 2.66 | G24: =+TICKET!E30 -> 33.6 | H24: =+F24*G24 -> 89.376
... A27: =+TICKET!D33 -> DYFCE-70 | B27: =IF(A27="","",IF(ISERROR(VLOOKUP(A27,'[7]LISTA DE PRECIOS'!B$7:E$1788,2,0)),"",VLOOKUP(A27,'[7]LISTA DE PRECIOS'!B$7:E$1788,2,0))) -> FLUIDO COMPLETACION ESPECIAL TIPO 7 | E27: =IF(A27="","",IF(ISERROR(VLOOKUP(A27,'[7]LISTA DE PRECIOS'!B$7:E$1788,3,0)),"",VLOOKUP(A27,'[7]LISTA DE PRECIOS'!B$7:E$1788,3,0))) -> bbl | F27: =IF(A27="","",IF(ISERROR(VLOOKUP(A27,'[7]LISTA DE PRECIOS'!B$7:E$1788,4,0)),"",VLOOKUP(A27,'[7]LISTA DE PRECIOS'!B$7:E$1788,4,0))) -> 34.9 | G27: =+TICKET!E33 -> 90 | H27: =+F27*G27 -> 3141
B29: =IF(A29="","",IF(ISERROR(VLOOKUP(A29,'[7]LISTA DE PRECIOS'!B$7:E$1788,2,0)),"",VLOOKUP(A29,'[7]LISTA DE PRECIOS'!B$7:E$1788,2,0))) | F29: Valor de la OT: | H29: =SUM(H1:H28) -> 25947.616
B30: Fecha de Inicio: | C30: 46234
B31: Fecha de Terminación: | C31: 46235
A33: REPRESENTANTE DE LA CONTRATISTA (Delegado): | E33: REPRESENTANTE DE EP PETROECUADOR (Delegado):
A34: Nombre: | B34: Ab. Mónica Rojas | E34: Nombre: | F34: =+[6]TICKET!E9 -> Ing. Mónica Quisnancela
A35: Cargo: | B35: Representante Legal | E35: Cargo: | F35: Ingeniero de Operaciones Activo

Sheet TICKET
F1: PREFACTURA | K1: Fecha de Aprobación: 03-07-2026 Revisión: 0
B7: FECHA: | E7: =IF(H12="","",H12) -> 46235 | K7: 4349 | O7: <>
B8: CLIENTE: | E8: EMPRESA PUBLICA DE HIDROCARBUROS DEL ECUADOR EP PETROECUADOR | K8: Condiciones de servicio: Los daños totales o parciales de equipos y/o herramientas, días de espera, equipos y personal, suspensión de trabajo o demás situaciones que pudieran presentarse durante la operación, estarán sujetas a los términos y condiciones del contrato bajo el cual se oferta el presente servicio
B9: SOLICITADO POR: | E9: Ing. Mónica Quisnancela
B10: Verbal | D10: ( ) | E10: Escrita via email | F10: ( x )
B11: NUMERO DE CONTRATO: | E11: 2025201
B12: INICIO TRABAJO: | E12: 46234 | G12: TRABAJO TERMINADO: | H12: 46235
B14: CAMPO / BLOQUE: | E14: GACELA | G14: BLOQUE 07
B15: POZO: | E15: GCLH-022 | G15: GACELA-H022
B16: TALADRO: | E16: RIGLESS
B17: OBSERVACIONES: | E17: BOMBEO SISTEMA SOLVENTE ACIDO
B18: ITEM | D18: CODIGO | E18: CANTIDAD | F18: UNIDAD | G18: DESCRIPCION | K18: PRECIO UNITARIO | L18: PRECIO TOTAL | M18: Tipo | N18: Material | O18: Servicio
B19: 1 | D19: SFC33001 | E19: 33.6 | F19: =IF(D19="","",IF(ISERROR(VLOOKUP(D19,LPPEC,3,0)),"",VLOOKUP(D19,LPPEC,3,0))) -> km | G19: =IF(D19="","",IF(ISERROR(VLOOKUP(D19,LPPEC,2,0)),"",VLOOKUP(D19,LPPEC,2,0))) -> Movilización unidad de bombeo para fluidos de completación | K19: =IF(D19="","",IF(ISERROR(VLOOKUP(D19,LPPEC,4,0)),"",VLOOKUP(D19,LPPEC,4,0))) -> 3.15 | L19: =IF(OR(D19="",E19=""),"",ROUND(E19*K19,2)) -> 105.84 | M19: =IF(D19="","",IF(ISERROR(VLOOKUP(D19,LPPEC,5,0)),"",VLOOKUP(D19,LPPEC,5,0))) -> Servicio | N19: =+IF($M19=N$18,$L19,0) -> 0 | O19: =+IF($M19=O$18,$L19,0) -> 105.84 | P19: CISTERNA
B20: =+B19+1 -> 2 | D20: SB3240 | E20: 1 | F20: =IF(D20="","",IF(ISERROR(VLOOKUP(D20,LPPEC,3,0)),"",VLOOKUP(D20,LPPEC,3,0))) -> unidad | G20: =IF(D20="","",IF(ISERROR(VLOOKUP(D20,LPPEC,2,0)),"",VLOOKUP(D20,LPPEC,2,0))) -> Cargo básico, primeras 4 horas o fracción de bombeo unidad de estimulación (700 HP) | K20: =IF(D20="","",IF(ISERROR(VLOOKUP(D20,LPPEC,4,0)),"",VLOOKUP(D20,LPPEC,4,0))) -> 3180.54 | L20: =IF(OR(D20="",E20=""),"",ROUND(E20*K20,2)) -> 3180.54 | M20: =IF(D20="","",IF(ISERROR(VLOOKUP(D20,LPPEC,5,0)),"",VLOOKUP(D20,LPPEC,5,0))) -> Servicio | N20: =+IF($M20=N$18,$L20,0) -> 0 | O20: =+IF($M20=O$18,$L20,0) -> 3180.54
B21: =+B20+1 -> 3 | D21: SFC33024 | E21: 1 | F21: =IF(D21="","",IF(ISERROR(VLOOKUP(D21,LPPEC,3,0)),"",VLOOKUP(D21,LPPEC,3,0))) -> unidad | G21: =IF(D21="","",IF(ISERROR(VLOOKUP(D21,LPPEC,2,0)),"",VLOOKUP(D21,LPPEC,2,0))) -> Tanque para ácido o solvente de 6500 galones, por trabajo | K21: =IF(D21="","",IF(ISERROR(VLOOKUP(D21,LPPEC,4,0)),"",VLOOKUP(D21,LPPEC,4,0))) -> 773.77 | L21: =IF(OR(D21="",E21=""),"",ROUND(E21*K21,2)) -> 773.77 | M21: =IF(D21="","",IF(ISERROR(VLOOKUP(D21,LPPEC,5,0)),"",VLOOKUP(D21,LPPEC,5,0))) -> Servicio | N21: =+IF($M21=N$18,$L21,0) -> 0 | O21: =+IF($M21=O$18,$L21,0) -> 773.77
B22: =+B21+1 -> 4 | D22: SFC33032 | E22: 1 | F22: =IF(D22="","",IF(ISERROR(VLOOKUP(D22,LPPEC,3,0)),"",VLOOKUP(D22,LPPEC,3,0))) -> día | G22: =IF(D22="","",IF(ISERROR(VLOOKUP(D22,LPPEC,2,0)),"",VLOOKUP(D22,LPPEC,2,0))) -> Supervisor Senior para fluidos de completación dia o fraccion | K22: =IF(D22="","",IF(ISERROR(VLOOKUP(D22,LPPEC,4,0)),"",VLOOKUP(D22,LPPEC,4,0))) -> 833.41 | L22: =IF(OR(D22="",E22=""),"",ROUND(E22*K22,2)) -> 833.41 | M22: =IF(D22="","",IF(ISERROR(VLOOKUP(D22,LPPEC,5,0)),"",VLOOKUP(D22,LPPEC,5,0))) -> Servicio | N22: =+IF($M22=N$18,$L22,0) -> 0 | O22: =+IF($M22=O$18,$L22,0) -> 833.41 | P22: JAVIER GUEVARA
B23: =+B22+1 -> 5 | D23: SFC33017 | E23: 1 | F23: =IF(D23="","",IF(ISERROR(VLOOKUP(D23,LPPEC,3,0)),"",VLOOKUP(D23,LPPEC,3,0))) -> día | G23: =IF(D23="","",IF(ISERROR(VLOOKUP(D23,LPPEC,2,0)),"",VLOOKUP(D23,LPPEC,2,0))) -> Operador para fluidos de completación dia o fraccion | K23: =IF(D23="","",IF(ISERROR(VLOOKUP(D23,LPPEC,4,0)),"",VLOOKUP(D23,LPPEC,4,0))) -> 349.78 | L23: =IF(OR(D23="",E23=""),"",ROUND(E23*K23,2)) -> 349.78 | M23: =IF(D23="","",IF(ISERROR(VLOOKUP(D23,LPPEC,5,0)),"",VLOOKUP(D23,LPPEC,5,0))) -> Servicio | N23: =+IF($M23=N$18,$L23,0) -> 0 | O23: =+IF($M23=O$18,$L23,0) -> 349.78 | P23: JEFERSON LEMACHE
B24: =+B23+1 -> 6 | D24: SFC33017 | E24: 1 | F24: =IF(D24="","",IF(ISERROR(VLOOKUP(D24,LPPEC,3,0)),"",VLOOKUP(D24,LPPEC,3,0))) -> día | G24: =IF(D24="","",IF(ISERROR(VLOOKUP(D24,LPPEC,2,0)),"",VLOOKUP(D24,LPPEC,2,0))) -> Operador para fluidos de completación dia o fraccion | K24: =IF(D24="","",IF(ISERROR(VLOOKUP(D24,LPPEC,4,0)),"",VLOOKUP(D24,LPPEC,4,0))) -> 349.78 | L24: =IF(OR(D24="",E24=""),"",ROUND(E24*K24,2)) -> 349.78 | M24: =IF(D24="","",IF(ISERROR(VLOOKUP(D24,LPPEC,5,0)),"",VLOOKUP(D24,LPPEC,5,0))) -> Servicio | N24: =+IF($M24=N$18,$L24,0) -> 0 | O24: =+IF($M24=O$18,$L24,0) -> 349.78 | P24: CRISTIAN REINO
B25: =+B24+1 -> 7 | D25: SFC33014 | E25: 1 | F25: =IF(D25="","",IF(ISERROR(VLOOKUP(D25,LPPEC,3,0)),"",VLOOKUP(D25,LPPEC,3,0))) -> día | G25: =IF(D25="","",IF(ISERROR(VLOOKUP(D25,LPPEC,2,0)),"",VLOOKUP(D25,LPPEC,2,0))) -> Tarifa de monitoreo en unidad de bombeo Presión, Densidad, Caudal, Volumen | K25: =IF(D25="","",IF(ISERROR(VLOOKUP(D25,LPPEC,4,0)),"",VLOOKUP(D25,LPPEC,4,0))) -> 373.74 | L25: =IF(OR(D25="",E25=""),"",ROUND(E25*K25,2)) -> 373.74 | M25: =IF(D25="","",IF(ISERROR(VLOOKUP(D25,LPPEC,5,0)),"",VLOOKUP(D25,LPPEC,5,0))) -> Servicio | N25: =+IF($M25=N$18,$L25,0) -> 0 | O25: =+IF($M25=O$18,$L25,0) -> 373.74
B26: =+B25+1 -> 8 | D26: SFC33011 | E26: 4200 | F26: =IF(D26="","",IF(ISERROR(VLOOKUP(D26,LPPEC,3,0)),"",VLOOKUP(D26,LPPEC,3,0))) -> gls | G26: =IF(D26="","",IF(ISERROR(VLOOKUP(D26,LPPEC,2,0)),"",VLOOKUP(D26,LPPEC,2,0))) -> Bombeo de fluidos no corrosivos de 2500 hasta 4200 galones | K26: =IF(D26="","",IF(ISERROR(VLOOKUP(D26,LPPEC,4,0)),"",VLOOKUP(D26,LPPEC,4,0))) -> 0.38 | L26: =IF(OR(D26="",E26=""),"",ROUND(E26*K26,2)) -> 1596 | M26: =IF(D26="","",IF(ISERROR(VLOOKUP(D26,LPPEC,5,0)),"",VLOOKUP(D26,LPPEC,5,0))) -> Servicio | N26: =+IF($M26=N$18,$L26,0) -> 0 | O26: =+IF($M26=O$18,$L26,0) -> 1596
B27: =+B26+1 -> 9 | D27: SFC33007 | E27: 840 | F27: =IF(D27="","",IF(ISERROR(VLOOKUP(D27,LPPEC,3,0)),"",VLOOKUP(D27,LPPEC,3,0))) -> gls | G27: =IF(D27="","",IF(ISERROR(VLOOKUP(D27,LPPEC,2,0)),"",VLOOKUP(D27,LPPEC,2,0))) -> Servicio de Bombeo de ácido primeros 2500 galones | K27: =IF(D27="","",IF(ISERROR(VLOOKUP(D27,LPPEC,4,0)),"",VLOOKUP(D27,LPPEC,4,0))) -> 0.34 | L27: =IF(OR(D27="",E27=""),"",ROUND(E27*K27,2)) -> 285.6 | M27: =IF(D27="","",IF(ISERROR(VLOOKUP(D27,LPPEC,5,0)),"",VLOOKUP(D27,LPPEC,5,0))) -> Servicio | N27: =+IF($M27=N$18,$L27,0) -> 0 | O27: =+IF($M27=O$18,$L27,0) -> 285.6
B28: =+B27+1 -> 10 | D28: SFC33027 | E28: 33.6 | F28: =IF(D28="","",IF(ISERROR(VLOOKUP(D28,LPPEC,3,0)),"",VLOOKUP(D28,LPPEC,3,0))) -> km | G28: =IF(D28="","",IF(ISERROR(VLOOKUP(D28,LPPEC,2,0)),"",VLOOKUP(D28,LPPEC,2,0))) -> Movilización de equipo adicional, unidades pesadas. | K28: =IF(D28="","",IF(ISERROR(VLOOKUP(D28,LPPEC,4,0)),"",VLOOKUP(D28,LPPEC,4,0))) -> 3.15 | L28: =IF(OR(D28="",E28=""),"",ROUND(E28*K28,2)) -> 105.84 | M28: =IF(D28="","",IF(ISERROR(VLOOKUP(D28,LPPEC,5,0)),"",VLOOKUP(D28,LPPEC,5,0))) -> Servicio | N28: =+IF($M28=N$18,$L28,0) -> 0 | O28: =+IF($M28=O$18,$L28,0) -> 105.84
B29: =+B28+1 -> 11 | D29: SFC33027 | E29: 33.6 | F29: =IF(D29="","",IF(ISERROR(VLOOKUP(D29,LPPEC,3,0)),"",VLOOKUP(D29,LPPEC,3,0))) -> km | G29: =IF(D29="","",IF(ISERROR(VLOOKUP(D29,LPPEC,2,0)),"",VLOOKUP(D29,LPPEC,2,0))) -> Movilización de equipo adicional, unidades pesadas. | K29: =IF(D29="","",IF(ISERROR(VLOOKUP(D29,LPPEC,4,0)),"",VLOOKUP(D29,LPPEC,4,0))) -> 3.15 | L29: =IF(OR(D29="",E29=""),"",ROUND(E29*K29,2)) -> 105.84 | M29: =IF(D29="","",IF(ISERROR(VLOOKUP(D29,LPPEC,5,0)),"",VLOOKUP(D29,LPPEC,5,0))) -> Servicio | N29: =+IF($M29=N$18,$L29,0) -> 0 | O29: =+IF($M29=O$18,$L29,0) -> 105.84 | P29: CAMION CON QUIMICA
B30: =+B29+1 -> 12 | D30: SFC33026 | E30: 33.6 | F30: =IF(D30="","",IF(ISERROR(VLOOKUP(D30,LPPEC,3,0)),"",VLOOKUP(D30,LPPEC,3,0))) -> km | G30: =IF(D30="","",IF(ISERROR(VLOOKUP(D30,LPPEC,2,0)),"",VLOOKUP(D30,LPPEC,2,0))) -> Movilización unidades livianas para personal | K30: =IF(D30="","",IF(ISERROR(VLOOKUP(D30,LPPEC,4,0)),"",VLOOKUP(D30,LPPEC,4,0))) -> 2.66 | L30: =IF(OR(D30="",E30=""),"",ROUND(E30*K30,2)) -> 89.38 | M30: =IF(D30="","",IF(ISERROR(VLOOKUP(D30,LPPEC,5,0)),"",VLOOKUP(D30,LPPEC,5,0))) -> Servicio | N30: =+IF($M30=N$18,$L30,0) -> 0 | O30: =+IF($M30=O$18,$L30,0) -> 89.38
B31: =+B30+1 -> 13 | D31: DYTERP-150 | E31: 110 | F31: =IF(D31="","",IF(ISERROR(VLOOKUP(D31,LPPEC,3,0)),"",VLOOKUP(D31,LPPEC,3,0))) -> gls | G31: =IF(D31="","",IF(ISERROR(VLOOKUP(D31,LPPEC,2,0)),"",VLOOKUP(D31,LPPEC,2,0))) -> Solvente Base Terpenos biodegradable | K31: =IF(D31="","",IF(ISERROR(VLOOKUP(D31,LPPEC,4,0)),"",VLOOKUP(D31,LPPEC,4,0))) -> 35.73 | L31: =IF(OR(D31="",E31=""),"",ROUND(E31*K31,2)) -> 3930.3 | M31: =IF(D31="","",IF(ISERROR(VLOOKUP(D31,LPPEC,5,0)),"",VLOOKUP(D31,LPPEC,5,0))) -> Material | N31: =+IF($M31=N$18,$L31,0) -> 3930.3 | O31: =+IF($M31=O$18,$L31,0) -> 0
B32: =+B31+1 -> 14 | D32: DYMBA-100 | E32: 840 | F32: =IF(D32="","",IF(ISERROR(VLOOKUP(D32,LPPEC,3,0)),"",VLOOKUP(D32,LPPEC,3,0))) -> gls | G32: =IF(D32="","",IF(ISERROR(VLOOKUP(D32,LPPEC,2,0)),"",VLOOKUP(D32,LPPEC,2,0))) -> SISTEMA REMOVEDOR DE CARBONATOS ORGÁNICO | K32: =IF(D32="","",IF(ISERROR(VLOOKUP(D32,LPPEC,4,0)),"",VLOOKUP(D32,LPPEC,4,0))) -> 12.77 | L32: =IF(OR(D32="",E32=""),"",ROUND(E32*K32,2)) -> 10726.8 | M32: =IF(D32="","",IF(ISERROR(VLOOKUP(D32,LPPEC,5,0)),"",VLOOKUP(D32,LPPEC,5,0))) -> Material | N32: =+IF($M32=N$18,$L32,0) -> 10726.8 | O32: =+IF($M32=O$18,$L32,0) -> 0
B33: =+B32+1 -> 15 | D33: DYFCE-70 | E33: 90 | F33: =IF(D33="","",IF(ISERROR(VLOOKUP(D33,LPPEC,3,0)),"",VLOOKUP(D33,LPPEC,3,0))) -> bbl | G33: =IF(D33="","",IF(ISERROR(VLOOKUP(D33,LPPEC,2,0)),"",VLOOKUP(D33,LPPEC,2,0))) -> FLUIDO COMPLETACION ESPECIAL TIPO 7 | K33: =IF(D33="","",IF(ISERROR(VLOOKUP(D33,LPPEC,4,0)),"",VLOOKUP(D33,LPPEC,4,0))) -> 34.9 | L33: =IF(OR(D33="",E33=""),"",ROUND(E33*K33,2)) -> 3141 | M33: =IF(D33="","",IF(ISERROR(VLOOKUP(D33,LPPEC,5,0)),"",VLOOKUP(D33,LPPEC,5,0))) -> Material | N33: =+IF($M33=N$18,$L33,0) -> 3141 | O33: =+IF($M33=O$18,$L33,0) -> 0
B34: Los precios no incluyen IVA | G34: Subtotal materiales: | H34: =+N34 -> 17798.1 | I34: Subtotal Servicios: | J34: =+O34 -> 8149.52 | K34: SUBTOTAL | L34: =SUM(L19:L33) -> 25947.62 | N34: =SUM(N19:N33) -> 17798.1 | O34: =SUM(O19:O33) -> 8149.52
K36: TOTAL | L36: =L34-L35 -> 25947.62
B37: Firma electrónica autorizada por Dynadrill Ecuador C.A.: ILDA ZAMBRANO | N37: 285626.27
D43: Representante Dynadrill Ecuador C.A.: | J43: Aprobado Cliente | K43: Ingeniero de Operaciones | N43: =IF(K44="","",IF(ISERROR(VLOOKUP(K44,BD!CD$2:CG$118,3,0)),"",VLOOKUP(K44,BD!CD$2:CG$118,3,0))) -> Ingeniero de Operaciones | O43: =+IF(K43=N43,"OK","Revisar") -> OK
D44: Nombre: | E44: Javier Guevara | J44: Nombre : | K44: Ing. Jorge Cruz
D45: C.I.: | E45: =IF(E44="","",IF(ISERROR(VLOOKUP(E44,BD!BZ$2:CA$23,2,0)),"",VLOOKUP(E44,BD!BZ$2:CA$23,2,0))) -> 1713206843 | J45: C.I.: | N45: =IF(K44="","",IF(ISERROR(VLOOKUP(K44,BD!CD$2:CG$118,2,0)),"",VLOOKUP(K44,BD!CD$2:CG$118,2,0))) -> 1205792391 | O45: =+IF(K45=N45,"OK","Revisar") -> Revisar

Sheet Reporte Job 
E1: REPORTE DIARIO DE ACTIVIDADES DE OPERACIONES | I1: Fecha de Aprobación: 03-07-2026
I2: Revisión: 0
B4: Fecha: | E4: =+TICKET!H12 -> 46235 | I4: Nº | J4: =IF([5]TICKET!K7="","",[5]TICKET!K7) -> 4349
B5: Cliente: | E5: =+[5]TICKET!E8 -> EMPRESA PUBLICA DE HIDROCARBUROS DEL ECUADOR EP PETROECUADOR | H5: Orden/Contrato Nº: | J5: =+TICKET!E11 -> 2025201
B6: Pozo: | E6: =+TICKET!E15 -> GCLH-022 | I6: Representante del Cliente: | J6: =+TICKET!K44 -> Ing. Jorge Cruz
B7: Campo/Bloque: | E7: =IF([5]TICKET!E14="","",[5]TICKET!E14&" / "&[5]TICKET!G14) -> GACELA / BLOQUE 07 | I7: Cargo: | J7: =IF([5]TICKET!K43="","",[5]TICKET!K43) -> Ingeniero de Operaciones
B8: Taladro: | E8: =IF([5]TICKET!E16="","",[5]TICKET!E16) -> RIGLESS
B9: DURACIÓN | E9: DETALLE DE ACTIVIDADES | N9: Horas OPE
B10: Inicio | C10: Fin | D10: Horas | N10: PUMP
B11: 46234
B12: 0.625 | C12: 0.66666667 | D12: =IF(OR(B12="",C12=""),0,IF(AND(B12<>"",C12<>"",B12<C12),(C12-B12)*24,IF(AND(B12<>"",C12<>"",B12>C12),((C12-B12)*24)+24,IF(B12-C12=0,24,"Error")))) -> 1 | E12: Personal y equipos de Cia Dynadrill arriban al pozo GCLH-022. Coordina trabajo con Ingeniero de Operaciones. Gestiona permiso de trabajo y realiza reunión de seguridad con todo personal involucrado. Cia Dynadrill ubica las siguientes unidades: 1 Unidad de bombeo (700 HP) 1 Tanque 6500 galones 1 Camión Plataforma con accesorios de bomba y quimica 1 Camioneta para movimiento del personal
B13: 0.66666667 | C13: 0.75 | D13: =IF(OR(B13="",C13=""),0,IF(AND(B13<>"",C13<>"",B13<C13),(C13-B13)*24,IF(AND(B13<>"",C13<>"",B13>C13),((C13-B13)*24)+24,IF(B13-C13=0,24,"Error")))) -> 2 | E13: Personal de Cia Dynadrill realiza rig up de equipos, arma linea de 4" desde tanque de 6500 galones hacia Unidad de Bombeo, desde Unidad de Bombeo arma linea de alta presion de 2" Fig 1502 hacia cabezal del pozo. Se instala monitoreo en Unidad de Bombeo de Presion, Densidad, Caudal y Volumen. Realiza prueba de presion con 2000 psi por 5 min. OK. En simultaneo se recibe 310 galones de Jp1 en tanque de 6500 galones de Cia Dynadrill. | N13: 0.5
B14: 0.75 | C14: 0.79166667 | D14: =IF(OR(B14="",C14=""),0,IF(AND(B14<>"",C14<>"",B14<C14),(C14-B14)*24,IF(AND(B14<>"",C14<>"",B14>C14),((C14-B14)*24)+24,IF(B14-C14=0,24,"Error")))) -> 1 | E14: Con autorizacion del cliente, se prepara tratamiento solvente-acido de acuerdo a la siguiente tabla:
F15: FASE SOLVENTE | I15: 10
F16: JP1 | G16: =IF(F16="","",IF(ISERROR(VLOOKUP(F16,[8]LP!B$6:E$1799,2,0)),"",VLOOKUP(F16,[8]LP!B$6:E$1799,2,0))) | I16: 310
F17: DYTERP-150 | G17: =IF(F17="","",IF(ISERROR(VLOOKUP(F17,[8]LP!B$6:E$1799,2,0)),"",VLOOKUP(F17,[8]LP!B$6:E$1799,2,0))) -> Solvente Base Terpenos biodegradable | I17: 110
F19: FASE ACIDO ORGANICO | I19: 20
F20: DYMBA-100 | G20: =IF(F20="","",IF(ISERROR(VLOOKUP(F20,[8]LP!B$6:E$1799,2,0)),"",VLOOKUP(F20,[8]LP!B$6:E$1799,2,0))) -> SISTEMA REMOVEDOR DE CARBONATOS ORGÁNICO | I20: =I19*42 -> 840
F22: FLUIDO DE CONTROL ESPECIAL | I22: 90
F23: DYFCE-70 | G23: =IF(F23="","",IF(ISERROR(VLOOKUP(F23,[8]LP!B$6:E$1799,2,0)),"",VLOOKUP(F23,[8]LP!B$6:E$1799,2,0))) -> FLUIDO COMPLETACION ESPECIAL TIPO 7 | I23: =I22 -> 90
E24: Nota: Se utiliza tanque de 6500 galones de Cia Dynadrill.
B25: 0.79166667 | C25: 0.91666667 | D25: =IF(OR(B25="",C25=""),0,IF(AND(B25<>"",C25<>"",B25<C25),(C25-B25)*24,IF(AND(B25<>"",C25<>"",B25>C25),((C25-B25)*24)+24,IF(B25-C25=0,24,"Error")))) -> 3 | E25: Con Unidad de Bombeo de Cia Dynadrill se bombea 10 bbl de sistema solvente y 20 bbl de sistema acido organico hacia profundidad de camisa (10149 ft) a 1,0 bpm y 150 psi de presion de circulacion. Se desplaza con 70 bls de fluido de completacion especial tipo 7 a 1,0 bpm con 150 psi inicial y termina desplazamiento con 350 psi. Posteriormente cierra anulares y forza sistema acido organico desplazandolos con 20 bbl de fluido de completación especial tipo 7 a 0,9 bpm y 350 psi de presion de circulacion. Se deja tratamiento y se espera 6 horas. Nota: La operación se registró en unidad de monitoreo de presión, densidad, caudal y volumen de Cia Dynadrill (1 día ítem SFC33014) | N25: 3
B27: 0.91666667 | C27: 0.95833333 | D27: =IF(OR(B27="",C27=""),0,IF(AND(B27<>"",C27<>"",B27<C27),(C27-B27)*24,IF(AND(B27<>"",C27<>"",B27>C27),((C27-B27)*24)+24,IF(B27-C27=0,24,"Error")))) -> 1 | E27: Tratamiento químico en reposo en el pozo. Personal de Cia Dynadrill realiza rig down de unidades, orden y limpieza en locacion.
B28: 0.95833333 | C28: 0.25 | D28: =IF(OR(B28="",C28=""),0,IF(AND(B28<>"",C28<>"",B28<C28),(C28-B28)*24,IF(AND(B28<>"",C28<>"",B28>C28),((C28-B28)*24)+24,IF(B28-C28=0,24,"Error")))) -> 7 | E28: Personal y equipos de Cia Dynadrill en espera de dispoción del cliente.
B29: 46235
B30: 0.25 | C30: 0.58333333 | D30: =IF(OR(B30="",C30=""),0,IF(AND(B30<>"",C30<>"",B30<C30),(C30-B30)*24,IF(AND(B30<>"",C30<>"",B30>C30),((C30-B30)*24)+24,IF(B30-C30=0,24,"Error")))) -> 8 | E30: Corrida # 01 se acopla pilling tool de 2,5" bajan a recuperar bomba jet de 2,81. Corrida # 02 se cambia pines y nuevamente se acopla pilling tool de 2,5 y bajan a intentar recuperar bomba jet de 2,81. Corrida # 03 se cambia pines y nuevamente se acopla pilling tool de 2,5" y bajan a intentar recuperar bomba jet de 2,81. Personal y equipos de Cía Dynadrill con autorización del cleinte se retira a Base coca.
E31: Por
E32: Bombeo de Fluidos corrosivos aplicable al Ítem SFC33007: | M32: =M31-4 -> -4
E33: SISTEMA ACIDO | H33: 20
E34: TOTAL FLUIDOS CORROSIVOS BOMBEADO SFC33007: | H34: =SUM(H33:H33) -> 20 | I34: =+H34*42 -> 840
E35: Bombeo de Fluidos no corrosivo aplicable al Ítem SFC33011:
E36: SISTEMA SOLVENTE | H36: 10
E37: FLUIDO DE CONTROL | H37: 70
E38: DESPLAZAMIENTO | H38: 20
E39: TOTAL FLUIDOS NO CORROSIVOS BOMBEADO Ítem SFC33011: | H39: =SUM(H36:H38) -> 100 | I39: =+H39*42 -> 4200
B41: Tiempo productivo: | E41: =SUM(D11:D39) -> 23 | G41: Tiempo No productivo: | H41: 0 | I41: Tiempo Total: | K41: =+E41+H41 -> 23 | N41: =SUM(N11:N40) -> 3.5
B42: Observaciones:
E43: =IF(N41=0,"La Unidad de Bombeo no registra aun horas de trabajo",IF(N41>4,"El tiempo de operación de la Unidad de Bombeo son "&N41&" horas"&" equivalentes a 1 cargo básico y "&N51&" horas","El tiempo de operación aplicable de la Unidad de Bombeo es un cargo básico por las primeras 4 horas o fracción de operación")) -> El tiempo de operación aplicable de la Unidad de Bombeo es un cargo básico por las primeras 4 horas o fracción de operación
E44: El tiempo aplicable al personal en la operación de Bombeo Solvente Acido es de dos días (31/07/2026) (01/08/2026)
E45: Equipos: Unidad de Bombeo, Tanque de 6500 galones
E46: Unidad Pesada para transportar unidad de bombeo: Tráiler Plataforma Hino placas QAA-3112
E47: Unidad Pesada para transportar tanque de 6500 galones: Tráiler Plataforma Internacional placas QAA-1793
E48: Unidad para transportar accesorios y química: Camión Plataforma CHEVROLET placa PDR - 7543
E49: Unidad liviana para transporte de personal: Camioneta CHEVROLET placa PFI-5569
E50: =+TICKET!B37 -> Firma electrónica autorizada por Dynadrill Ecuador C.A.: ILDA ZAMBRANO | N50: 4
B51: Nombre: | E51: =+[5]TICKET!E44 -> Javier Guevara | G51: Nombre: | H51: =+[5]TICKET!K44 -> Ing. Jorge Cruz | N51: =+IF(N41=0,"",N41-N50) -> -0.5
B52: Firma: | G52: Firma: | H52: =+[5]TICKET!K43 -> Ingeniero de Operaciones
B53: C.I.: | E53: =+[5]TICKET!E45 -> 1713206843 | G53: C.I.: | H53: =+[5]TICKET!K45 -> 0

Sheet GUIA
B12: CLIENTE: | D12: EMPRESA PUBLICA DE HIDROCARBUROS DEL ECUADOR EP PETROECUADOR | F12: RUC: 1768153530001 | H12: HORA SALIDA:
B13: SOLICITADO POR: | D13: =TICKET!E9 -> Ing. Mónica Quisnancela
B14: DESPACHADO POR: | D14: Carlos Calderon | H14: HORA LLEGADA:
B15: LUGAR DE ORIGEN: Coca Base Dynadrill | F15: DATOS DE LA PERSONA ENCARGADA DEL TRANSPORTE
B16: CAMPO: | D16: GACELA | F16: NOMBRE O RAZÓN SOCIAL: | G16: Javier Guevara
B17: POZO: | D17: =+TICKET!E15 -> GCLH-022 | F17: RUC / CEDULA: 1713206843 | G17: FIRMA: …………………………..
B18: FECHA: | D18: 46234 | F18: VEHICULO: Camion Chevrolet NQR | G18: PLACAS: | H18: PDR-7543 | M18: X
B19: ITEM | C19: CANTIDAD | D19: SERIAL/CODIGO | E19: UNIDAD DE MEDIDA | F19: DESCRIPCION | M19: Validador
B20: =+IF(D20="","",1) -> 1 | C20: =+TICKET!E31 -> 110 | D20: =TICKET!D31 -> DYTERP-150 | E20: =IF(D20="","",IF(ISERROR(VLOOKUP(D20,[3]LP!B$6:E$1799,3,0)),"",VLOOKUP(D20,[3]LP!B$6:E$1799,3,0))) -> gls | F20: =IF(D20="","",IF(ISERROR(VLOOKUP(D20,[3]LP!B$6:E$1799,2,0)),"",VLOOKUP(D20,[3]LP!B$6:E$1799,2,0))) -> Solvente Base Terpenos biodegradable | M20: =IF(D20="","",IF(ISERROR(VLOOKUP(D20,LPPEC,5,0)),"",VLOOKUP(D20,LPPEC,5,0))) -> Material
B21: =+IF(D21="","",1) -> 1 | C21: =+TICKET!E32 -> 840 | D21: =TICKET!D32 -> DYMBA-100 | E21: =IF(D21="","",IF(ISERROR(VLOOKUP(D21,[3]LP!B$6:E$1799,3,0)),"",VLOOKUP(D21,[3]LP!B$6:E$1799,3,0))) -> gls | F21: =IF(D21="","",IF(ISERROR(VLOOKUP(D21,[3]LP!B$6:E$1799,2,0)),"",VLOOKUP(D21,[3]LP!B$6:E$1799,2,0))) -> SISTEMA REMOVEDOR DE CARBONATOS ORGÁNICO | M21: =IF(D21="","",IF(ISERROR(VLOOKUP(D21,LPPEC,5,0)),"",VLOOKUP(D21,LPPEC,5,0))) -> Material
B22: =+IF(D22="","",1) -> 1 | C22: =+TICKET!E33 -> 90 | D22: =TICKET!D33 -> DYFCE-70 | E22: =IF(D22="","",IF(ISERROR(VLOOKUP(D22,[3]LP!B$6:E$1799,3,0)),"",VLOOKUP(D22,[3]LP!B$6:E$1799,3,0))) -> bbl | F22: =IF(D22="","",IF(ISERROR(VLOOKUP(D22,[3]LP!B$6:E$1799,2,0)),"",VLOOKUP(D22,[3]LP!B$6:E$1799,2,0))) -> FLUIDO COMPLETACION ESPECIAL TIPO 7 | M22: =IF(D22="","",IF(ISERROR(VLOOKUP(D22,LPPEC,5,0)),"",VLOOKUP(D22,LPPEC,5,0))) -> Material
M23: =IF(D23="","",IF(ISERROR(VLOOKUP(D23,LPPEC,5,0)),"",VLOOKUP(D23,LPPEC,5,0)))
M24: =IF(D24="","",IF(ISERROR(VLOOKUP(D24,LPPEC,5,0)),"",VLOOKUP(D24,LPPEC,5,0)))
B25: =IF(AND(B$20=1,D25<>""),#REF!+1,"") | E25: =IF(D25="","",IF(ISERROR(VLOOKUP(D25,[3]LP!B$6:E$1799,3,0)),"",VLOOKUP(D25,[3]LP!B$6:E$1799,3,0))) | F25: =IF(D25="","",IF(ISERROR(VLOOKUP(D25,[3]LP!B$6:E$1799,2,0)),"",VLOOKUP(D25,[3]LP!B$6:E$1799,2,0))) | M25: =IF(D25="","",IF(ISERROR(VLOOKUP(D25,LPPEC,5,0)),"",VLOOKUP(D25,LPPEC,5,0)))
C29: x
C30: Entregue Conforme | G30: Recibi Conforme
C31: =+[3]TICKET!E86 -> Carlos Poveda | F31: Nombre: | G31: =+TICKET!K44 -> Ing. Jorge Cruz
F32: Cargo: | G32: =+[3]TICKET!K85 -> Ingeniero de Operaciones
F33: CI: | G33: =+[3]TICKET!K87 -> #REF!

Sheet BD Pozos
G4: DOCUMENTO: | H4: REGISTRO DE POZOS EN OPEN WELLS
G5: FUENTE: | H5: EDM - OPEN WELLS & REGISTRO OFICIAL DE PAM NOMENCLATURAS DE POZOS
G6: ELABORADO: | H6: GERENCIMIENTO DE DATOS
A7: BLOQUE | B7: ACTIVO | C7: CAMPO | D7: PAD | E7: NOMBRE LARGO POZO | F7: NOMBRE CORTO POZO | G7: WELLBORE | H7: BLOQUE ID | I7: BLOQUE | J7: ACTIVO | K7: CAMPO | L7: PAD | M7: NOMBRE LARGO POZO | N7: Tipo
A8: B01 | B8: LA | C8: PACOA | D8: PAD | E8: PACOA-023 | F8: PAC-023 | G8: PAC-023 | H8: =+A8 -> B01 | I8: =IF(ISERROR(VLOOKUP(H8,BD!BN$2:BO$51,2,FALSE)),"",VLOOKUP(H8,BD!BN$2:BO$51,2,FALSE)) -> BLOQUE 01 | J8: =IF(B8="","",B8) -> LA | K8: =+C8 -> PACOA | L8: =+D8 -> PAD | M8: =+IF(F8=F7,E8&RIGHT(G8,2),E8) -> PACOA-023 | N8: Open Wells
A9: B01 | B9: LA | C9: PACOA | D9: PAD | E9: SAN PABLO-001 | F9: SNP-001 | G9: SNP-001 | H9: =+A9 -> B01 | I9: =IF(ISERROR(VLOOKUP(H9,BD!BN$2:BO$51,2,FALSE)),"",VLOOKUP(H9,BD!BN$2:BO$51,2,FALSE)) -> BLOQUE 01 | J9: =IF(B9="","",B9) -> LA | K9: =+C9 -> PACOA | L9: =+D9 -> PAD | M9: =+IF(F9=F8,E9&RIGHT(G9,2),E9) -> SAN PABLO-001 | N9: Open Wells
A10: B01 | B10: LA | C10: PACOA | D10: PAD | E10: PACOA-002 | F10: PAC-002 | G10: PAC-002 | H10: =+A10 -> B01 | I10: =IF(ISERROR(VLOOKUP(H10,BD!BN$2:BO$51,2,FALSE)),"",VLOOKUP(H10,BD!BN$2:BO$51,2,FALSE)) -> BLOQUE 01 | J10: =IF(B10="","",B10) -> LA | K10: =+C10 -> PACOA | L10: =+D10 -> PAD | M10: =+IF(F10=F9,E10&RIGHT(G10,2),E10) -> PACOA-002 | N10: Open Wells
A11: B01 | B11: LA | C11: PACOA | D11: PAD | E11: PACOA-004 | F11: PAC-004 | G11: PAC-004 | H11: =+A11 -> B01 | I11: =IF(ISERROR(VLOOKUP(H11,BD!BN$2:BO$51,2,FALSE)),"",VLOOKUP(H11,BD!BN$2:BO$51,2,FALSE)) -> BLOQUE 01 | J11: =IF(B11="","",B11) -> LA | K11: =+C11 -> PACOA | L11: =+D11 -> PAD | M11: =+IF(F11=F10,E11&RIGHT(G11,2),E11) -> PACOA-004 | N11: Open Wells
A12: B01 | B12: LA | C12: PACOA | D12: PAD | E12: PACOA-005 | F12: PAC-005 | G12: PAC-005 | H12: =+A12 -> B01 | I12: =IF(ISERROR(VLOOKUP(H12,BD!BN$2:BO$51,2,FALSE)),"",VLOOKUP(H12,BD!BN$2:BO$51,2,FALSE)) -> BLOQUE 01 | J12: =IF(B12="","",B12) -> LA | K12: =+C12 -> PACOA | L12: =+D12 -> PAD | M12: =+IF(F12=F11,E12&RIGHT(G12,2),E12) -> PACOA-005 | N12: Open Wells
A13: B01 | B13: LA | C13: PACOA | D13: PAD | E13: PACOA-008 | F13: PAC-008 | G13: PAC-008 | H13: =+A13 -> B01 | I13: =IF(ISERROR(VLOOKUP(H13,BD!BN$2:BO$51,2,FALSE)),"",VLOOKUP(H13,BD!BN$2:BO$51,2,FALSE)) -> BLOQUE 01 | J13: =IF(B13="","",B13) -> LA | K13: =+C13 -> PACOA | L13: =+D13 -> PAD | M13: =+IF(F13=F12,E13&RIGHT(G13,2),E13) -> PACOA-008 | N13: Open Wells
A14: B01 | B14: LA | C14: PACOA | D14: PAD | E14: PACOA-007 | F14: PAC-007 | G14: PAC-007 | H14: =+A14 -> B01 | I14: =IF(ISERROR(VLOOKUP(H14,BD!BN$2:BO$51,2,FALSE)),"",VLOOKUP(H14,BD!BN$2:BO$51,2,FALSE)) -> BLOQUE 01 | J14: =IF(B14="","",B14) -> LA | K14: =+C14 -> PACOA | L14: =+D14 -> PAD | M14: =+IF(F14=F13,E14&RIGHT(G14,2),E14) -> PACOA-007 | N14: Open Wells
A15: B01 | B15: LA | C15: PACOA | D15: PAD | E15: PACOA-016 | F15: PAC-016 | G15: PAC-016 | H15: =+A15 -> B01 | I15: =IF(ISERROR(VLOOKUP(H15,BD!BN$2:BO$51,2,FALSE)),"",VLOOKUP(H15,BD!BN$2:BO$51,2,FALSE)) -> BLOQUE 01 | J15: =IF(B15="","",B15) -> LA | K15: =+C15 -> PACOA | L15: =+D15 -> PAD | M15: =+IF(F15=F14,E15&RIGHT(G15,2),E15) -> PACOA-016 | N15: Open Wells
A16: B01 | B16: LA | C16: PACOA | D16: PAD | E16: PACOA-017 | F16: PAC-017 | G16: PAC-017 | H16: =+A16 -> B01 | I16: =IF(ISERROR(VLOOKUP(H16,BD!BN$2:BO$51,2,FALSE)),"",VLOOKUP(H16,BD!BN$2:BO$51,2,FALSE)) -> BLOQUE 01 | J16: =IF(B16="","",B16) -> LA | K16: =+C16 -> PACOA | L16: =+D16 -> PAD | M16: =+IF(F16=F15,E16&RIGHT(G16,2),E16) -> PACOA-017 | N16: Open Wells
A17: B01 | B17: LA | C17: PACOA | D17: PAD | E17: PACOA-024 | F17: PAC-024 | G17: PAC-024 | H17: =+A17 -> B01 | I17: =IF(ISERROR(VLOOKUP(H17,BD!BN$2:BO$51,2,FALSE)),"",VLOOKUP(H17,BD!BN$2:BO$51,2,FALSE)) -> BLOQUE 01 | J17: =IF(B17="","",B17) -> LA | K17: =+C17 -> PACOA | L17: =+D17 -> PAD | M17: =+IF(F17=F16,E17&RIGHT(G17,2),E17) -> PACOA-024 | N17: Open Wells
A18: B01 | B18: LA | C18: PACOA | D18: PAD | E18: PACOA-036 | F18: PAC-036 | G18: PAC-036 | H18: =+A18 -> B01 | I18: =IF(ISERROR(VLOOKUP(H18,BD!BN$2:BO$51,2,FALSE)),"",VLOOKUP(H18,BD!BN$2:BO$51,2,FALSE)) -> BLOQUE 01 | J18: =IF(B18="","",B18) -> LA | K18: =+C18 -> PACOA | L18: =+D18 -> PAD | M18: =+IF(F18=F17,E18&RIGHT(G18,2),E18) -> PACOA-036 | N18: Open Wells
A19: B01 | B19: LA | C19: PACOA | D19: PAD | E19: PACOA-033 | F19: PAC-033 | G19: PAC-033 | H19: =+A19 -> B01 | I19: =IF(ISERROR(VLOOKUP(H19,BD!BN$2:BO$51,2,FALSE)),"",VLOOKUP(H19,BD!BN$2:BO$51,2,FALSE)) -> BLOQUE 01 | J19: =IF(B19="","",B19) -> LA | K19: =+C19 -> PACOA | L19: =+D19 -> PAD | M19: =+IF(F19=F18,E19&RIGHT(G19,2),E19) -> PACOA-033 | N19: Open Wells
... A293: B07 | B293: OY | C293: OSO | D293: PAD G | E293: OSO-G063H | F293: OSOG-063H | G293: OSOG-063H | H293: =+A293 -> B07 | I293: =IF(ISERROR(VLOOKUP(H293,BD!BN$2:BO$51,2,FALSE)),"",VLOOKUP(H293,BD!BN$2:BO$51,2,FALSE)) -> BLOQUE 07 | J293: =IF(B293="","",B293) -> OY | K293: =+C293 -> OSO | L293: =+D293 -> PAD G | M293: =+IF(F293=F292,E293&RIGHT(G293,2),E293) -> OSO-G063H | N293: Open Wells
A294: B07 | B294: OY | C294: OSO | D294: PAD G | E294: OSO-G063H | F294: OSOG-063H | G294: OSOG-063HR1 | H294: =+A294 -> B07 | I294: =IF(ISERROR(VLOOKUP(H294,BD!BN$2:BO$51,2,FALSE)),"",VLOOKUP(H294,BD!BN$2:BO$51,2,FALSE)) -> BLOQUE 07 | J294: =IF(B294="","",B294) -> OY | K294: =+C294 -> OSO | L294: =+D294 -> PAD G | M294: =+IF(F294=F293,E294&RIGHT(G294,2),E294) -> OSO-G063HR1 | N294: Updated Open wells | P294: Difiere de Open Wells, prima el registro oficial
A295: B07 | B295: OY | C295: OSO | D295: PAD G | E295: OSO-G063H | F295: OSOG-063H | G295: OSOG-063HS1 | H295: =+A295 -> B07 | I295: =IF(ISERROR(VLOOKUP(H295,BD!BN$2:BO$51,2,FALSE)),"",VLOOKUP(H295,BD!BN$2:BO$51,2,FALSE)) -> BLOQUE 07 | J295: =IF(B295="","",B295) -> OY | K295: =+C295 -> OSO | L295: =+D295 -> PAD G | M295: =+IF(F295=F294,E295&RIGHT(G295,2),E295) -> OSO-G063HS1 | N295: Updated Open wells | P295: Difiere de Open Wells, prima el registro oficial
A296: B07 | B296: OY | C296: OSO | D296: PAD G | E296: OSO-G063H | F296: OSOG-063H | G296: OSOG-063HS2 | H296: =+A296 -> B07 | I296: =IF(ISERROR(VLOOKUP(H296,BD!BN$2:BO$51,2,FALSE)),"",VLOOKUP(H296,BD!BN$2:BO$51,2,FALSE)) -> BLOQUE 07 | J296: =IF(B296="","",B296) -> OY | K296: =+C296 -> OSO | L296: =+D296 -> PAD G | M296: =+IF(F296=F295,E296&RIGHT(G296,2),E296) -> OSO-G063HS2 | N296: Registro oficial PAM
A297: B07 | B297: OY | C297: OSO | D297: PAD G | E297: OSO-G081 | F297: OSOG-081 | G297: OSOG-081 | H297: =+A297 -> B07 | I297: =IF(ISERROR(VLOOKUP(H297,BD!BN$2:BO$51,2,FALSE)),"",VLOOKUP(H297,BD!BN$2:BO$51,2,FALSE)) -> BLOQUE 07 | J297: =IF(B297="","",B297) -> OY | K297: =+C297 -> OSO | L297: =+D297 -> PAD G | M297: =+IF(F297=F296,E297&RIGHT(G297,2),E297) -> OSO-G081 | N297: Open Wells
A298: B07 | B298: OY | C298: OSO | D298: PAD G | E298: OSO-G097 | F298: OSOG-097 | G298: OSOG-097 | H298: =+A298 -> B07 | I298: =IF(ISERROR(VLOOKUP(H298,BD!BN$2:BO$51,2,FALSE)),"",VLOOKUP(H298,BD!BN$2:BO$51,2,FALSE)) -> BLOQUE 07 | J298: =IF(B298="","",B298) -> OY | K298: =+C298 -> OSO | L298: =+D298 -> PAD G | M298: =+IF(F298=F297,E298&RIGHT(G298,2),E298) -> OSO-G097 | N298: Open Wells
A299: B07 | B299: OY | C299: OSO | D299: PAD G | E299: OSO-G067 | F299: OSOG-067 | G299: OSOG-067 | H299: =+A299 -> B07 | I299: =IF(ISERROR(VLOOKUP(H299,BD!BN$2:BO$51,2,FALSE)),"",VLOOKUP(H299,BD!BN$2:BO$51,2,FALSE)) -> BLOQUE 07 | J299: =IF(B299="","",B299) -> OY | K299: =+C299 -> OSO | L299: =+D299 -> PAD G | M299: =+IF(F299=F298,E299&RIGHT(G299,2),E299) -> OSO-G067 | N299: Open Wells
A300: B07 | B300: OY | C300: OSO | D300: PAD G | E300: OSO-G067 | F300: OSOG-067 | G300: OSOG-067R1 | H300: =+A300 -> B07 | I300: =IF(ISERROR(VLOOKUP(H300,BD!BN$2:BO$51,2,FALSE)),"",VLOOKUP(H300,BD!BN$2:BO$51,2,FALSE)) -> BLOQUE 07 | J300: =IF(B300="","",B300) -> OY | K300: =+C300 -> OSO | L300: =+D300 -> PAD G | M300: =+IF(F300=F299,E300&RIGHT(G300,2),E300) -> OSO-G067R1 | N300: Open Wells
A301: B07 | B301: OY | C301: OSO | D301: PAD G | E301: OSO-G086H | F301: OSOG-086H | G301: OSOG-086H | H301: =+A301 -> B07 | I301: =IF(ISERROR(VLOOKUP(H301,BD!BN$2:BO$51,2,FALSE)),"",VLOOKUP(H301,BD!BN$2:BO$51,2,FALSE)) -> BLOQUE 07 | J301: =IF(B301="","",B301) -> OY | K301: =+C301 -> OSO | L301: =+D301 -> PAD G | M301: =+IF(F301=F300,E301&RIGHT(G301,2),E301) -> OSO-G086H | N301: Open Wells
A302: B07 | B302: OY | C302: OSO | D302: PAD G | E302: OSO-G086H | F302: OSOG-086H | G302: OSOG-086S1 | H302: =+A302 -> B07 | I302: =IF(ISERROR(VLOOKUP(H302,BD!BN$2:BO$51,2,FALSE)),"",VLOOKUP(H302,BD!BN$2:BO$51,2,FALSE)) -> BLOQUE 07 | J302: =IF(B302="","",B302) -> OY | K302: =+C302 -> OSO | L302: =+D302 -> PAD G | M302: =+IF(F302=F301,E302&RIGHT(G302,2),E302) -> OSO-G086HS1 | N302: Open Wells
A303: B07 | B303: OY | C303: OSO | D303: PAD G | E303: OSO-G086H | F303: OSOG-086H | G303: OSOG-086S2 | H303: =+A303 -> B07 | I303: =IF(ISERROR(VLOOKUP(H303,BD!BN$2:BO$51,2,FALSE)),"",VLOOKUP(H303,BD!BN$2:BO$51,2,FALSE)) -> BLOQUE 07 | J303: =IF(B303="","",B303) -> OY | K303: =+C303 -> OSO | L303: =+D303 -> PAD G | M303: =+IF(F303=F302,E303&RIGHT(G303,2),E303) -> OSO-G086HS2 | N303: Open Wells
A304: B07 | B304: OY | C304: OSO | D304: PAD G | E304: OSO-G089H | F304: OSOG-089H | G304: OSOG-089H | H304: =+A304 -> B07 | I304: =IF(ISERROR(VLOOKUP(H304,BD!BN$2:BO$51,2,FALSE)),"",VLOOKUP(H304,BD!BN$2:BO$51,2,FALSE)) -> BLOQUE 07 | J304: =IF(B304="","",B304) -> OY | K304: =+C304 -> OSO | L304: =+D304 -> PAD G | M304: =+IF(F304=F303,E304&RIGHT(G304,2),E304) -> OSO-G089H | N304: Open Wells
A305: B07 | B305: OY | C305: OSO | D305: PAD G | E305: OSO-G069 | F305: OSOG-069 | G305: OSOG-069 | H305: =+A305 -> B07 | I305: =IF(ISERROR(VLOOKUP(H305,BD!BN$2:BO$51,2,FALSE)),"",VLOOKUP(H305,BD!BN$2:BO$51,2,FALSE)) -> BLOQUE 07 | J305: =IF(B305="","",B305) -> OY | K305: =+C305 -> OSO | L305: =+D305 -> PAD G | M305: =+IF(F305=F304,E305&RIGHT(G305,2),E305) -> OSO-G069 | N305: Open Wells
A306: B07 | B306: OY | C306: OSO | D306: PAD G | E306: OSO-G061 | F306: OSOG-061 | G306: OSOG-061 | H306: =+A306 -> B07 | I306: =IF(ISERROR(VLOOKUP(H306,BD!BN$2:BO$51,2,FALSE)),"",VLOOKUP(H306,BD!BN$2:BO$51,2,FALSE)) -> BLOQUE 07 | J306: =IF(B306="","",B306) -> OY | K306: =+C306 -> OSO | L306: =+D306 -> PAD G | M306: =+IF(F306=F305,E306&RIGHT(G306,2),E306) -> OSO-G061 | N306: Open Wells
A307: B07 | B307: OY | C307: OSO | D307: PAD G | E307: OSO-G065 | F307: OSOG-065 | G307: OSOG-065 | H307: =+A307 -> B07 | I307: =IF(ISERROR(VLOOKUP(H307,BD!BN$2:BO$51,2,FALSE)),"",VLOOKUP(H307,BD!BN$2:BO$51,2,FALSE)) -> BLOQUE 07 | J307: =IF(B307="","",B307) -> OY | K307: =+C307 -> OSO | L307: =+D307 -> PAD G | M307: =+IF(F307=F306,E307&RIGHT(G307,2),E307) -> OSO-G065 | N307: Open Wells
... A392: B07 | B392: OY | C392: PUNINO | D392: PAD A | E392: PUNINO-A001 | F392: PNNA-001 | G392: PNNA-001 | H392: =+A392 -> B07 | I392: =IF(ISERROR(VLOOKUP(H392,BD!BN$2:BO$51,2,FALSE)),"",VLOOKUP(H392,BD!BN$2:BO$51,2,FALSE)) -> BLOQUE 07 | J392: =IF(B392="","",B392) -> OY | K392: =+C392 -> PUNINO | L392: =+D392 -> PAD A | M392: =+IF(F392=F391,E392&RIGHT(G392,2),E392) -> PUNINO-A001 | N392: Open Wells
A393: B10 | C393: OGLAN ANGLO | D393: PAD | E393: OGLAN ANGLO-001 | F393: OGA-001 | G393: OGA-001 | H393: =+A393 -> B10 | I393: =IF(ISERROR(VLOOKUP(H393,BD!BN$2:BO$51,2,FALSE)),"",VLOOKUP(H393,BD!BN$2:BO$51,2,FALSE)) -> BLOQUE 10 | J393: =IF(B393="","",B393) | K393: =+C393 -> OGLAN ANGLO | L393: =+D393 -> PAD | M393: =+IF(F393=F392,E393&RIGHT(G393,2),E393) -> OGLAN ANGLO-001 | N393: Open Wells
A394: B11 | C394: CAMINO | D394: PAD | E394: CAMINO-001 | F394: CMN-001 | G394: CMN-001 | H394: =+A394 -> B11 | I394: =IF(ISERROR(VLOOKUP(H394,BD!BN$2:BO$51,2,FALSE)),"",VLOOKUP(H394,BD!BN$2:BO$51,2,FALSE)) -> BLOQUE 11 | J394: =IF(B394="","",B394) | K394: =+C394 -> CAMINO | L394: =+D394 -> PAD | M394: =+IF(F394=F393,E394&RIGHT(G394,2),E394) -> CAMINO-001 | N394: Open Wells
A395: B11 | C395: OCHENTA | D395: PAD | E395: OCHENTA-001 | F395: OCH-001 | G395: OCH-001 | H395: =+A395 -> B11 | I395: =IF(ISERROR(VLOOKUP(H395,BD!BN$2:BO$51,2,FALSE)),"",VLOOKUP(H395,BD!BN$2:BO$51,2,FALSE)) -> BLOQUE 11 | J395: =IF(B395="","",B395) | K395: =+C395 -> OCHENTA | L395: =+D395 -> PAD | M395: =+IF(F395=F394,E395&RIGHT(G395,2),E395) -> OCHENTA-001 | N395: Open Wells
A396: B11 | C396: PUSINO | D396: PAD | E396: PUSINO-001 | F396: PSN-001 | G396: PSN-001 | H396: =+A396 -> B11 | I396: =IF(ISERROR(VLOOKUP(H396,BD!BN$2:BO$51,2,FALSE)),"",VLOOKUP(H396,BD!BN$2:BO$51,2,FALSE)) -> BLOQUE 11 | J396: =IF(B396="","",B396) | K396: =+C396 -> PUSINO | L396: =+D396 -> PAD | M396: =+IF(F396=F395,E396&RIGHT(G396,2),E396) -> PUSINO-001 | N396: Open Wells
A397: B12 | B397: EY | C397: COCAYA CENTRO | D397: PAD A | E397: COCAYA CENTRO-A001 | F397: CCCA-001 | G397: CCCA-001 | H397: =+A397 -> B12 | I397: =IF(ISERROR(VLOOKUP(H397,BD!BN$2:BO$51,2,FALSE)),"",VLOOKUP(H397,BD!BN$2:BO$51,2,FALSE)) -> BLOQUE 12 | J397: =IF(B397="","",B397) -> EY | K397: =+C397 -> COCAYA CENTRO | L397: =+D397 -> PAD A | M397: =+IF(F397=F396,E397&RIGHT(G397,2),E397) -> COCAYA CENTRO-A001 | N397: Open Wells
A398: B12 | B398: EY | C398: DUMBIQUE | D398: PAD A | E398: DUMBIQUE-A003 | F398: DMBA-003 | G398: DMBA-003 | H398: =+A398 -> B12 | I398: =IF(ISERROR(VLOOKUP(H398,BD!BN$2:BO$51,2,FALSE)),"",VLOOKUP(H398,BD!BN$2:BO$51,2,FALSE)) -> BLOQUE 12 | J398: =IF(B398="","",B398) -> EY | K398: =+C398 -> DUMBIQUE | L398: =+D398 -> PAD A | M398: =+IF(F398=F397,E398&RIGHT(G398,2),E398) -> DUMBIQUE-A003 | N398: Open Wells
A399: B12 | B399: EY | C399: DUMBIQUE | D399: PAD A | E399: DUMBIQUE-A002I | F399: DMBA-002I | G399: DMBA-002I | H399: =+A399 -> B12 | I399: =IF(ISERROR(VLOOKUP(H399,BD!BN$2:BO$51,2,FALSE)),"",VLOOKUP(H399,BD!BN$2:BO$51,2,FALSE)) -> BLOQUE 12 | J399: =IF(B399="","",B399) -> EY | K399: =+C399 -> DUMBIQUE | L399: =+D399 -> PAD A | M399: =+IF(F399=F398,E399&RIGHT(G399,2),E399) -> DUMBIQUE-A002I | N399: Open Wells
A400: B12 | B400: EY | C400: DUMBIQUE | D400: PAD A | E400: DUMBIQUE-A001 | F400: DMBA-001 | G400: DMBA-001 | H400: =+A400 -> B12 | I400: =IF(ISERROR(VLOOKUP(H400,BD!BN$2:BO$51,2,FALSE)),"",VLOOKUP(H400,BD!BN$2:BO$51,2,FALSE)) -> BLOQUE 12 | J400: =IF(B400="","",B400) -> EY | K400: =+C400 -> DUMBIQUE | L400: =+D400 -> PAD A | M400: =+IF(F400=F399,E400&RIGHT(G400,2),E400) -> DUMBIQUE-A001 | N400: Open Wells
A401: B12 | B401: EY | C401: DUMBIQUE | D401: PAD A | E401: DUMBIQUE-A004 | F401: DMBA-004 | G401: DMBA-004 | H401: =+A401 -> B12 | I401: =IF(ISERROR(VLOOKUP(H401,BD!BN$2:BO$51,2,FALSE)),"",VLOOKUP(H401,BD!BN$2:BO$51,2,FALSE)) -> BLOQUE 12 | J401: =IF(B401="","",B401) -> EY | K401: =+C401 -> DUMBIQUE | L401: =+D401 -> PAD A | M401: =+IF(F401=F400,E401&RIGHT(G401,2),E401) -> DUMBIQUE-A004 | N401: Open Wells
A402: B12 | B402: EY | C402: DUMBIQUE SUR | D402: PAD A | E402: DUMBIQUE SUR-A001 | F402: DMSA-001 | G402: DMSA-001 | H402: =+A402 -> B12 | I402: =IF(ISERROR(VLOOKUP(H402,BD!BN$2:BO$51,2,FALSE)),"",VLOOKUP(H402,BD!BN$2:BO$51,2,FALSE)) -> BLOQUE 12 | J402: =IF(B402="","",B402) -> EY | K402: =+C402 -> DUMBIQUE SUR | L402: =+D402 -> PAD A | M402: =+IF(F402=F401,E402&RIGHT(G402,2),E402) -> DUMBIQUE SUR-A001 | N402: Open Wells
A403: B12 | B403: EY | C403: EDEN YUTURI | D403: PAD A | E403: EDEN YUTURI-A001 | F403: EDYA-001 | G403: EDYA-001 | H403: =+A403 -> B12 | I403: =IF(ISERROR(VLOOKUP(H403,BD!BN$2:BO$51,2,FALSE)),"",VLOOKUP(H403,BD!BN$2:BO$51,2,FALSE)) -> BLOQUE 12 | J403: =IF(B403="","",B403) -> EY | K403: =+C403 -> EDEN YUTURI | L403: =+D403 -> PAD A | M403: =+IF(F403=F402,E403&RIGHT(G403,2),E403) -> EDEN YUTURI-A001 | N403: Open Wells
A404: B12 | B404: EY | C404: EDEN YUTURI | D404: PAD A | E404: EDEN YUTURI-A002 | F404: EDYA-002 | G404: EDYA-002 | H404: =+A404 -> B12 | I404: =IF(ISERROR(VLOOKUP(H404,BD!BN$2:BO$51,2,FALSE)),"",VLOOKUP(H404,BD!BN$2:BO$51,2,FALSE)) -> BLOQUE 12 | J404: =IF(B404="","",B404) -> EY | K404: =+C404 -> EDEN YUTURI | L404: =+D404 -> PAD A | M404: =+IF(F404=F403,E404&RIGHT(G404,2),E404) -> EDEN YUTURI-A002 | N404: Open Wells
A405: B12 | B405: EY | C405: EDEN YUTURI | D405: PAD A | E405: EDEN YUTURI-A042 | F405: EDYA-042 | G405: EDYA-042 | H405: =+A405 -> B12 | I405: =IF(ISERROR(VLOOKUP(H405,BD!BN$2:BO$51,2,FALSE)),"",VLOOKUP(H405,BD!BN$2:BO$51,2,FALSE)) -> BLOQUE 12 | J405: =IF(B405="","",B405) -> EY | K405: =+C405 -> EDEN YUTURI | L405: =+D405 -> PAD A | M405: =+IF(F405=F404,E405&RIGHT(G405,2),E405) -> EDEN YUTURI-A042 | N405: Open Wells
A406: B12 | B406: EY | C406: EDEN YUTURI | D406: PAD A | E406: EDEN YUTURI-A060 | F406: EDYA-060 | G406: EDYA-060 | H406: =+A406 -> B12 | I406: =IF(ISERROR(VLOOKUP(H406,BD!BN$2:BO$51,2,FALSE)),"",VLOOKUP(H406,BD!BN$2:BO$51,2,FALSE)) -> BLOQUE 12 | J406: =IF(B406="","",B406) -> EY | K406: =+C406 -> EDEN YUTURI | L406: =+D406 -> PAD A | M406: =+IF(F406=F405,E406&RIGHT(G406,2),E406) -> EDEN YUTURI-A060 | N406: Open Wells
A407: B12 | B407: EY | C407: EDEN YUTURI | D407: PAD A | E407: EDEN YUTURI-A004 | F407: EDYA-004 | G407: EDYA-004 | H407: =+A407 -> B12 | I407: =IF(ISERROR(VLOOKUP(H407,BD!BN$2:BO$51,2,FALSE)),"",VLOOKUP(H407,BD!BN$2:BO$51,2,FALSE)) -> BLOQUE 12 | J407: =IF(B407="","",B407) -> EY | K407: =+C407 -> EDEN YUTURI | L407: =+D407 -> PAD A | M407: =+IF(F407=F406,E407&RIGHT(G407,2),E407) -> EDEN YUTURI-A004 | N407: Open Wells
A408: B12 | B408: EY | C408: EDEN YUTURI | D408: PAD A | E408: EDEN YUTURI-A054 | F408: EDYA-054 | G408: EDYA-054 | H408: =+A408 -> B12 | I408: =IF(ISERROR(VLOOKUP(H408,BD!BN$2:BO$51,2,FALSE)),"",VLOOKUP(H408,BD!BN$2:BO$51,2,FALSE)) -> BLOQUE 12 | J408: =IF(B408="","",B408) -> EY | K408: =+C408 -> EDEN YUTURI | L408: =+D408 -> PAD A | M408: =+IF(F408=F407,E408&RIGHT(G408,2),E408) -> EDEN YUTURI-A054 | N408: Open Wells
... A687: B12 | B687: EY | C687: YUTURI | D687: PAD A | E687: YUTURI-A001 | F687: YTRA-001 | G687: YTRA-001 | H687: =+A687 -> B12 | I687: =IF(ISERROR(VLOOKUP(H687,BD!BN$2:BO$51,2,FALSE)),"",VLOOKUP(H687,BD!BN$2:BO$51,2,FALSE)) -> BLOQUE 12 | J687: =IF(B687="","",B687) -> EY | K687: =+C687 -> YUTURI | L687: =+D687 -> PAD A | M687: =+IF(F687=F686,E687&RIGHT(G687,2),E687) -> YUTURI-A001 | N687: Open Wells
A688: B14 | C688: KUPI | D688: PAD | E688: KUPI-001 | F688: KUP-001 | G688: KUP-001 | H688: =+A688 -> B14 | I688: =IF(ISERROR(VLOOKUP(H688,BD!BN$2:BO$51,2,FALSE)),"",VLOOKUP(H688,BD!BN$2:BO$51,2,FALSE)) -> BLOQUE 14 | J688: =IF(B688="","",B688) | K688: =+C688 -> KUPI | L688: =+D688 -> PAD | M688: =+IF(F688=F687,E688&RIGHT(G688,2),E688) -> KUPI-001 | N688: Open Wells
A689: B14 | C689: KUPI | D689: PAD | E689: KUPI-003 | F689: KUP-003 | G689: KUP-003 | H689: =+A689 -> B14 | I689: =IF(ISERROR(VLOOKUP(H689,BD!BN$2:BO$51,2,FALSE)),"",VLOOKUP(H689,BD!BN$2:BO$51,2,FALSE)) -> BLOQUE 14 | J689: =IF(B689="","",B689) | K689: =+C689 -> KUPI | L689: =+D689 -> PAD | M689: =+IF(F689=F688,E689&RIGHT(G689,2),E689) -> KUPI-003 | N689: Open Wells
A690: B14 | C690: KUPI | D690: PAD | E690: KUPI-002 | F690: KUP-002 | G690: KUP-002 | H690: =+A690 -> B14 | I690: =IF(ISERROR(VLOOKUP(H690,BD!BN$2:BO$51,2,FALSE)),"",VLOOKUP(H690,BD!BN$2:BO$51,2,FALSE)) -> BLOQUE 14 | J690: =IF(B690="","",B690) | K690: =+C690 -> KUPI | L690: =+D690 -> PAD | M690: =+IF(F690=F689,E690&RIGHT(G690,2),E690) -> KUPI-002 | N690: Open Wells
A691: B14 | C691: NANTU | D691: PAD | E691: NANTU-002 | F691: NNT-002 | G691: NNT-002 | H691: =+A691 -> B14 | I691: =IF(ISERROR(VLOOKUP(H691,BD!BN$2:BO$51,2,FALSE)),"",VLOOKUP(H691,BD!BN$2:BO$51,2,FALSE)) -> BLOQUE 14 | J691: =IF(B691="","",B691) | K691: =+C691 -> NANTU | L691: =+D691 -> PAD | M691: =+IF(F691=F690,E691&RIGHT(G691,2),E691) -> NANTU-002 | N691: Open Wells
A692: B14 | C692: NANTU | D692: PAD | E692: NANTU-001 | F692: NNT-001 | G692: NNT-001 | H692: =+A692 -> B14 | I692: =IF(ISERROR(VLOOKUP(H692,BD!BN$2:BO$51,2,FALSE)),"",VLOOKUP(H692,BD!BN$2:BO$51,2,FALSE)) -> BLOQUE 14 | J692: =IF(B692="","",B692) | K692: =+C692 -> NANTU | L692: =+D692 -> PAD | M692: =+IF(F692=F691,E692&RIGHT(G692,2),E692) -> NANTU-001 | N692: Open Wells
A693: B14 | C693: SUNKA | D693: PAD | E693: SUNKA-001 | F693: SNK-001 | G693: SNK-001 | H693: =+A693 -> B14 | I693: =IF(ISERROR(VLOOKUP(H693,BD!BN$2:BO$51,2,FALSE)),"",VLOOKUP(H693,BD!BN$2:BO$51,2,FALSE)) -> BLOQUE 14 | J693: =IF(B693="","",B693) | K693: =+C693 -> SUNKA | L693: =+D693 -> PAD | M693: =+IF(F693=F692,E693&RIGHT(G693,2),E693) -> SUNKA-001 | N693: Open Wells
A694: B14 | C694: WANKE | D694: PAD | E694: WANKE-001 | F694: WNK-001 | G694: WNK-001 | H694: =+A694 -> B14 | I694: =IF(ISERROR(VLOOKUP(H694,BD!BN$2:BO$51,2,FALSE)),"",VLOOKUP(H694,BD!BN$2:BO$51,2,FALSE)) -> BLOQUE 14 | J694: =IF(B694="","",B694) | K694: =+C694 -> WANKE | L694: =+D694 -> PAD | M694: =+IF(F694=F693,E694&RIGHT(G694,2),E694) -> WANKE-001 | N694: Open Wells
A695: B15 | B695: IN | C695: ANGEL NORTE | D695: PAD A | E695: ANGEL NORTE-A002 | F695: ANNA-002 | G695: ANNA-002 | H695: =+A695 -> B15 | I695: =IF(ISERROR(VLOOKUP(H695,BD!BN$2:BO$51,2,FALSE)),"",VLOOKUP(H695,BD!BN$2:BO$51,2,FALSE)) -> BLOQUE 15 | J695: =IF(B695="","",B695) -> IN | K695: =+C695 -> ANGEL NORTE | L695: =+D695 -> PAD A | M695: =+IF(F695=F694,E695&RIGHT(G695,2),E695) -> ANGEL NORTE-A002 | N695: Open Wells
A696: B15 | B696: IN | C696: ANGEL NORTE | D696: PAD A | E696: ANGEL NORTE-A001 | F696: ANNA-001 | G696: ANNA-001 | H696: =+A696 -> B15 | I696: =IF(ISERROR(VLOOKUP(H696,BD!BN$2:BO$51,2,FALSE)),"",VLOOKUP(H696,BD!BN$2:BO$51,2,FALSE)) -> BLOQUE 15 | J696: =IF(B696="","",B696) -> IN | K696: =+C696 -> ANGEL NORTE | L696: =+D696 -> PAD A | M696: =+IF(F696=F695,E696&RIGHT(G696,2),E696) -> ANGEL NORTE-A001 | N696: Open Wells
A697: B15 | B697: IN | C697: COCAYA | D697: PAD A | E697: COCAYA-A001 | F697: CCYA-001 | G697: CCYA-001 | H697: =+A697 -> B15 | I697: =IF(ISERROR(VLOOKUP(H697,BD!BN$2:BO$51,2,FALSE)),"",VLOOKUP(H697,BD!BN$2:BO$51,2,FALSE)) -> BLOQUE 15 | J697: =IF(B697="","",B697) -> IN | K697: =+C697 -> COCAYA | L697: =+D697 -> PAD A | M697: =+IF(F697=F696,E697&RIGHT(G697,2),E697) -> COCAYA-A001 | N697: Open Wells
A698: B15 | B698: IN | C698: COCAYA | D698: PAD A | E698: COCAYA-A001 | F698: CCYA-001 | G698: CCYA-001S1 | H698: =+A698 -> B15 | I698: =IF(ISERROR(VLOOKUP(H698,BD!BN$2:BO$51,2,FALSE)),"",VLOOKUP(H698,BD!BN$2:BO$51,2,FALSE)) -> BLOQUE 15 | J698: =IF(B698="","",B698) -> IN | K698: =+C698 -> COCAYA | L698: =+D698 -> PAD A | M698: =+IF(F698=F697,E698&RIGHT(G698,2),E698) -> COCAYA-A001S1 | N698: Open Wells
A699: B15 | B699: IN | C699: CONCORDIA | D699: PAD A | E699: CONCORDIA-A003 | F699: CNCA-003 | G699: CNCA-003 | H699: =+A699 -> B15 | I699: =IF(ISERROR(VLOOKUP(H699,BD!BN$2:BO$51,2,FALSE)),"",VLOOKUP(H699,BD!BN$2:BO$51,2,FALSE)) -> BLOQUE 15 | J699: =IF(B699="","",B699) -> IN | K699: =+C699 -> CONCORDIA | L699: =+D699 -> PAD A | M699: =+IF(F699=F698,E699&RIGHT(G699,2),E699) -> CONCORDIA-A003 | N699: Open Wells
A700: B15 | B700: IN | C700: CONCORDIA | D700: PAD A | E700: CONCORDIA-A005 | F700: CNCA-005 | G700: CNCA-005 | H700: =+A700 -> B15 | I700: =IF(ISERROR(VLOOKUP(H700,BD!BN$2:BO$51,2,FALSE)),"",VLOOKUP(H700,BD!BN$2:BO$51,2,FALSE)) -> BLOQUE 15 | J700: =IF(B700="","",B700) -> IN | K700: =+C700 -> CONCORDIA | L700: =+D700 -> PAD A | M700: =+IF(F700=F699,E700&RIGHT(G700,2),E700) -> CONCORDIA-A005 | N700: Open Wells
A701: B15 | B701: IN | C701: CONCORDIA | D701: PAD A | E701: CONCORDIA-A001 | F701: CNCA-001 | G701: CNCA-001 | H701: =+A701 -> B15 | I701: =IF(ISERROR(VLOOKUP(H701,BD!BN$2:BO$51,2,FALSE)),"",VLOOKUP(H701,BD!BN$2:BO$51,2,FALSE)) -> BLOQUE 15 | J701: =IF(B701="","",B701) -> IN | K701: =+C701 -> CONCORDIA | L701: =+D701 -> PAD A | M701: =+IF(F701=F700,E701&RIGHT(G701,2),E701) -> CONCORDIA-A001 | N701: Open Wells
A702: B15 | B702: IN | C702: CONCORDIA | D702: PAD A | E702: CONCORDIA-A007 | F702: CNCA-007 | G702: CNCA-007 | H702: =+A702 -> B15 | I702: =IF(ISERROR(VLOOKUP(H702,BD!BN$2:BO$51,2,FALSE)),"",VLOOKUP(H702,BD!BN$2:BO$51,2,FALSE)) -> BLOQUE 15 | J702: =IF(B702="","",B702) -> IN | K702: =+C702 -> CONCORDIA | L702: =+D702 -> PAD A | M702: =+IF(F702=F701,E702&RIGHT(G702,2),E702) -> CONCORDIA-A007 | N702: Open Wells
A703: B15 | B703: IN | C703: CONCORDIA | D703: PAD A | E703: CONCORDIA-A002 | F703: CNCA-002 | G703: CNCA-002 | H703: =+A703 -> B15 | I703: =IF(ISERROR(VLOOKUP(H703,BD!BN$2:BO$51,2,FALSE)),"",VLOOKUP(H703,BD!BN$2:BO$51,2,FALSE)) -> BLOQUE 15 | J703: =IF(B703="","",B703) -> IN | K703: =+C703 -> CONCORDIA | L703: =+D703 -> PAD A | M703: =+IF(F703=F702,E703&RIGHT(G703,2),E703) -> CONCORDIA-A002 | N703: Open Wells
A704: B15 | B704: IN | C704: CONCORDIA | D704: PAD A | E704: CONCORDIA-A004 | F704: CNCA-004 | G704: CNCA-004 | H704: =+A704 -> B15 | I704: =IF(ISERROR(VLOOKUP(H704,BD!BN$2:BO$51,2,FALSE)),"",VLOOKUP(H704,BD!BN$2:BO$51,2,FALSE)) -> BLOQUE 15 | J704: =IF(B704="","",B704) -> IN | K704: =+C704 -> CONCORDIA | L704: =+D704 -> PAD A | M704: =+IF(F704=F703,E704&RIGHT(G704,2),E704) -> CONCORDIA-A004 | N704: Open Wells
A705: B15 | B705: IN | C705: INDILLANA | D705: PAD A | E705: INDILLANA-A014 | F705: INDA-014 | G705: INDA-014 | H705: =+A705 -> B15 | I705: =IF(ISERROR(VLOOKUP(H705,BD!BN$2:BO$51,2,FALSE)),"",VLOOKUP(H705,BD!BN$2:BO$51,2,FALSE)) -> BLOQUE 15 | J705: =IF(B705="","",B705) -> IN | K705: =+C705 -> INDILLANA | L705: =+D705 -> PAD A | M705: =+IF(F705=F704,E705&RIGHT(G705,2),E705) -> INDILLANA-A014 | N705: Open Wells
A706: B15 | B706: IN | C706: INDILLANA | D706: PAD A | E706: INDILLANA-A010 | F706: INDA-010 | G706: INDA-010 | H706: =+A706 -> B15 | I706: =IF(ISERROR(VLOOKUP(H706,BD!BN$2:BO$51,2,FALSE)),"",VLOOKUP(H706,BD!BN$2:BO$51,2,FALSE)) -> BLOQUE 15 | J706: =IF(B706="","",B706) -> IN | K706: =+C706 -> INDILLANA | L706: =+D706 -> PAD A | M706: =+IF(F706=F705,E706&RIGHT(G706,2),E706) -> INDILLANA-A010 | N706: Open Wells
... A802: B15 | B802: IN | C802: LIMONCOCHA | D802: PAD E | E802: LIMONCOCHA-E005 | F802: LMNE-005 | G802: LMNE-005 | H802: =+A802 -> B15 | I802: =IF(ISERROR(VLOOKUP(H802,BD!BN$2:BO$51,2,FALSE)),"",VLOOKUP(H802,BD!BN$2:BO$51,2,FALSE)) -> BLOQUE 15 | J802: =IF(B802="","",B802) -> IN | K802: =+C802 -> LIMONCOCHA | L802: =+D802 -> PAD E | M802: =+IF(F802=F801,E802&RIGHT(G802,2),E802) -> LIMONCOCHA-E005 | N802: Open Wells
A803: B15 | B803: IN | C803: LIMONCOCHA | D803: PAD E | E803: LIMONCOCHA-E005 | F803: LMNE-005 | G803: LMNE-005S1 | H803: =+A803 -> B15 | I803: =IF(ISERROR(VLOOKUP(H803,BD!BN$2:BO$51,2,FALSE)),"",VLOOKUP(H803,BD!BN$2:BO$51,2,FALSE)) -> BLOQUE 15 | J803: =IF(B803="","",B803) -> IN | K803: =+C803 -> LIMONCOCHA | L803: =+D803 -> PAD E | M803: =+IF(F803=F801,E803&RIGHT(G803,2),E803) -> LIMONCOCHA-E005 | N803: Open Wells
A804: B15 | B804: IN | C804: LIMONCOCHA | D804: PAD E | E804: LIMONCOCHA-E005S1 | F804: LMNE-005 | G804: LMNE-005S1R1 | H804: =+A804 -> B15 | I804: =IF(ISERROR(VLOOKUP(H804,BD!BN$2:BO$51,2,FALSE)),"",VLOOKUP(H804,BD!BN$2:BO$51,2,FALSE)) -> BLOQUE 15 | J804: =IF(B804="","",B804) -> IN | K804: =+C804 -> LIMONCOCHA | L804: =+D804 -> PAD E | M804: =+IF(F804=F802,E804&RIGHT(G804,2),E804) -> LIMONCOCHA-E005S1R1 | N804: Updated Open wells
A805: B15 | B805: IN | C805: LIMONCOCHA | D805: PAD F | E805: LIMONCOCHA-F006 | F805: LMNF-006 | G805: LMNF-006 | H805: =+A805 -> B15 | I805: =IF(ISERROR(VLOOKUP(H805,BD!BN$2:BO$51,2,FALSE)),"",VLOOKUP(H805,BD!BN$2:BO$51,2,FALSE)) -> BLOQUE 15 | J805: =IF(B805="","",B805) -> IN | K805: =+C805 -> LIMONCOCHA | L805: =+D805 -> PAD F | M805: =+IF(F805=F804,E805&RIGHT(G805,2),E805) -> LIMONCOCHA-F006 | N805: Open Wells
A806: B15 | B806: IN | C806: LIMONCOCHA | D806: PAD G | E806: LIMONCOCHA-G007 | F806: LMNG-007 | G806: LMNG-007 | H806: =+A806 -> B15 | I806: =IF(ISERROR(VLOOKUP(H806,BD!BN$2:BO$51,2,FALSE)),"",VLOOKUP(H806,BD!BN$2:BO$51,2,FALSE)) -> BLOQUE 15 | J806: =IF(B806="","",B806) -> IN | K806: =+C806 -> LIMONCOCHA | L806: =+D806 -> PAD G | M806: =+IF(F806=F805,E806&RIGHT(G806,2),E806) -> LIMONCOCHA-G007 | N806: Open Wells
A807: B15 | B807: IN | C807: LIMONCOCHA | D807: PAD G | E807: LIMONCOCHA-G036 | F807: LMNG-036 | G807: LMNG-036 | H807: =+A807 -> B15 | I807: =IF(ISERROR(VLOOKUP(H807,BD!BN$2:BO$51,2,FALSE)),"",VLOOKUP(H807,BD!BN$2:BO$51,2,FALSE)) -> BLOQUE 15 | J807: =IF(B807="","",B807) -> IN | K807: =+C807 -> LIMONCOCHA | L807: =+D807 -> PAD G | M807: =+IF(F807=F806,E807&RIGHT(G807,2),E807) -> LIMONCOCHA-G036 | N807: Open Wells
A808: B15 | B808: IN | C808: LIMONCOCHA | D808: PAD G | E808: LIMONCOCHA-G043 | F808: LMNG-043 | G808: LMNG-043 | H808: =+A808 -> B15 | I808: =IF(ISERROR(VLOOKUP(H808,BD!BN$2:BO$51,2,FALSE)),"",VLOOKUP(H808,BD!BN$2:BO$51,2,FALSE)) -> BLOQUE 15 | J808: =IF(B808="","",B808) -> IN | K808: =+C808 -> LIMONCOCHA | L808: =+D808 -> PAD G | M808: =+IF(F808=F807,E808&RIGHT(G808,2),E808) -> LIMONCOCHA-G043 | N808: Open Wells
A809: B15 | B809: IN | C809: LIMONCOCHA | D809: PAD G | E809: LIMONCOCHA-G044 | F809: LMNG-044 | G809: LMNG-044 | H809: =+A809 -> B15 | I809: =IF(ISERROR(VLOOKUP(H809,BD!BN$2:BO$51,2,FALSE)),"",VLOOKUP(H809,BD!BN$2:BO$51,2,FALSE)) -> BLOQUE 15 | J809: =IF(B809="","",B809) -> IN | K809: =+C809 -> LIMONCOCHA | L809: =+D809 -> PAD G | M809: =+IF(F809=F808,E809&RIGHT(G809,2),E809) -> LIMONCOCHA-G044 | N809: Open Wells
A810: B15 | B810: IN | C810: LIMONCOCHA | D810: PAD G | E810: LIMONCOCHA-G050H | F810: LMNG-050H | G810: LMNG-050H | H810: =+A810 -> B15 | I810: =IF(ISERROR(VLOOKUP(H810,BD!BN$2:BO$51,2,FALSE)),"",VLOOKUP(H810,BD!BN$2:BO$51,2,FALSE)) -> BLOQUE 15 | J810: =IF(B810="","",B810) -> IN | K810: =+C810 -> LIMONCOCHA | L810: =+D810 -> PAD G | M810: =+IF(F810=F809,E810&RIGHT(G810,2),E810) -> LIMONCOCHA-G050H | N810: Open Wells
A811: B15 | B811: IN | C811: LIMONCOCHA | D811: PAD G | E811: LIMONCOCHA-G051H | F811: LMNG-051H | G811: LMNG-051H | H811: =+A811 -> B15 | I811: =IF(ISERROR(VLOOKUP(H811,BD!BN$2:BO$51,2,FALSE)),"",VLOOKUP(H811,BD!BN$2:BO$51,2,FALSE)) -> BLOQUE 15 | J811: =IF(B811="","",B811) -> IN | K811: =+C811 -> LIMONCOCHA | L811: =+D811 -> PAD G | M811: =+IF(F811=F810,E811&RIGHT(G811,2),E811) -> LIMONCOCHA-G051H | N811: Open Wells
A812: B15 | B812: IN | C812: LIMONCOCHA | D812: PAD G | E812: LIMONCOCHA-G052 | F812: LMNG-052 | G812: LMNG-052 | H812: =+A812 -> B15 | I812: =IF(ISERROR(VLOOKUP(H812,BD!BN$2:BO$51,2,FALSE)),"",VLOOKUP(H812,BD!BN$2:BO$51,2,FALSE)) -> BLOQUE 15 | J812: =IF(B812="","",B812) -> IN | K812: =+C812 -> LIMONCOCHA | L812: =+D812 -> PAD G | M812: =+IF(F812=F811,E812&RIGHT(G812,2),E812) -> LIMONCOCHA-G052 | N812: Open Wells
A813: B15 | B813: IN | C813: LIMONCOCHA | D813: PAD G | E813: LIMONCOCHA-G053H | F813: LMNG-053H | G813: LMNG-053H | H813: =+A813 -> B15 | I813: =IF(ISERROR(VLOOKUP(H813,BD!BN$2:BO$51,2,FALSE)),"",VLOOKUP(H813,BD!BN$2:BO$51,2,FALSE)) -> BLOQUE 15 | J813: =IF(B813="","",B813) -> IN | K813: =+C813 -> LIMONCOCHA | L813: =+D813 -> PAD G | M813: =+IF(F813=F812,E813&RIGHT(G813,2),E813) -> LIMONCOCHA-G053H | N813: Open Wells
A814: B15 | B814: IN | C814: LIMONCOCHA | D814: PAD G | E814: LIMONCOCHA-G053H | F814: LMNG-053H | G814: LMNG-053HS1 | H814: =+A814 -> B15 | I814: =IF(ISERROR(VLOOKUP(H814,BD!BN$2:BO$51,2,FALSE)),"",VLOOKUP(H814,BD!BN$2:BO$51,2,FALSE)) -> BLOQUE 15 | J814: =IF(B814="","",B814) -> IN | K814: =+C814 -> LIMONCOCHA | L814: =+D814 -> PAD G | M814: =+IF(F814=F813,E814&RIGHT(G814,2),E814) -> LIMONCOCHA-G053HS1 | N814: Open Wells
A815: B15 | B815: IN | C815: LIMONCOCHA | D815: PAD G | E815: LIMONCOCHA-G054H | F815: LMNG-054H | G815: LMNG-054H | H815: =+A815 -> B15 | I815: =IF(ISERROR(VLOOKUP(H815,BD!BN$2:BO$51,2,FALSE)),"",VLOOKUP(H815,BD!BN$2:BO$51,2,FALSE)) -> BLOQUE 15 | J815: =IF(B815="","",B815) -> IN | K815: =+C815 -> LIMONCOCHA | L815: =+D815 -> PAD G | M815: =+IF(F815=F814,E815&RIGHT(G815,2),E815) -> LIMONCOCHA-G054H | N815: Open Wells
A816: B15 | B816: IN | C816: LIMONCOCHA | D816: PAD G | E816: LIMONCOCHA-G063 | F816: LMNG-063 | G816: LMNG-063 | H816: =+A816 -> B15 | I816: =IF(ISERROR(VLOOKUP(H816,BD!BN$2:BO$51,2,FALSE)),"",VLOOKUP(H816,BD!BN$2:BO$51,2,FALSE)) -> BLOQUE 15 | J816: =IF(B816="","",B816) -> IN | K816: =+C816 -> LIMONCOCHA | L816: =+D816 -> PAD G | M816: =+IF(F816=F815,E816&RIGHT(G816,2),E816) -> LIMONCOCHA-G063 | N816: Registro oficial PAM
... A1022: B15 | B1022: IN | C1022: YANAQUINCHA SUR | D1022: PAD A | E1022: YANAQUINCHA SUR-A001 | F1022: YNSA-001 | G1022: YNSA-001 | H1022: =+A1022 -> B15 | I1022: =IF(ISERROR(VLOOKUP(H1022,BD!BN$2:BO$51,2,FALSE)),"",VLOOKUP(H1022,BD!BN$2:BO$51,2,FALSE)) -> BLOQUE 15 | J1022: =IF(B1022="","",B1022) -> IN | K1022: =+C1022 -> YANAQUINCHA SUR | L1022: =+D1022 -> PAD A | M1022: =+IF(F1022=F1021,E1022&RIGHT(G1022,2),E1022) -> YANAQUINCHA SUR-A001 | N1022: Open Wells
A1023: B16 | C1023: AMO | D1023: PAD | E1023: AMO-001 | F1023: AMO-001 | G1023: AMO-001 | H1023: =+A1023 -> B16 | I1023: =IF(ISERROR(VLOOKUP(H1023,BD!BN$2:BO$51,2,FALSE)),"",VLOOKUP(H1023,BD!BN$2:BO$51,2,FALSE)) -> BLOQUE 16 | J1023: =IF(B1023="","",B1023) | K1023: =+C1023 -> AMO | L1023: =+D1023 -> PAD | M1023: =+IF(F1023=F1022,E1023&RIGHT(G1023,2),E1023) -> AMO-001 | N1023: Open Wells
A1024: B16 | C1024: BOGI | D1024: PAD | E1024: BOGI-001 | F1024: BOG-001 | G1024: BOG-001 | H1024: =+A1024 -> B16 | I1024: =IF(ISERROR(VLOOKUP(H1024,BD!BN$2:BO$51,2,FALSE)),"",VLOOKUP(H1024,BD!BN$2:BO$51,2,FALSE)) -> BLOQUE 16 | J1024: =IF(B1024="","",B1024) | K1024: =+C1024 -> BOGI | L1024: =+D1024 -> PAD | M1024: =+IF(F1024=F1023,E1024&RIGHT(G1024,2),E1024) -> BOGI-001 | N1024: Open Wells
A1025: B16 | C1025: CAPIRON | D1025: PAD | E1025: CAPIRON-001 | F1025: CPR-001 | G1025: CPR-001 | H1025: =+A1025 -> B16 | I1025: =IF(ISERROR(VLOOKUP(H1025,BD!BN$2:BO$51,2,FALSE)),"",VLOOKUP(H1025,BD!BN$2:BO$51,2,FALSE)) -> BLOQUE 16 | J1025: =IF(B1025="","",B1025) | K1025: =+C1025 -> CAPIRON | L1025: =+D1025 -> PAD | M1025: =+IF(F1025=F1024,E1025&RIGHT(G1025,2),E1025) -> CAPIRON-001 | N1025: Open Wells
A1026: B16 | C1026: CAPIRON NORTE | D1026: PAD | E1026: CAPIRON NORTE-001 | F1026: CPN-001 | G1026: CPN-001 | H1026: =+A1026 -> B16 | I1026: =IF(ISERROR(VLOOKUP(H1026,BD!BN$2:BO$51,2,FALSE)),"",VLOOKUP(H1026,BD!BN$2:BO$51,2,FALSE)) -> BLOQUE 16 | J1026: =IF(B1026="","",B1026) | K1026: =+C1026 -> CAPIRON NORTE | L1026: =+D1026 -> PAD | M1026: =+IF(F1026=F1025,E1026&RIGHT(G1026,2),E1026) -> CAPIRON NORTE-001 | N1026: Open Wells
A1027: B16 | C1027: DAIME | D1027: PAD | E1027: DAIME-001 | F1027: DAM-001 | G1027: DAM-001 | H1027: =+A1027 -> B16 | I1027: =IF(ISERROR(VLOOKUP(H1027,BD!BN$2:BO$51,2,FALSE)),"",VLOOKUP(H1027,BD!BN$2:BO$51,2,FALSE)) -> BLOQUE 16 | J1027: =IF(B1027="","",B1027) | K1027: =+C1027 -> DAIME | L1027: =+D1027 -> PAD | M1027: =+IF(F1027=F1026,E1027&RIGHT(G1027,2),E1027) -> DAIME-001 | N1027: Open Wells
A1028: B16 | C1028: DICARON | D1028: PAD | E1028: DICARON-001 | F1028: DCR-001 | G1028: DCR-001 | H1028: =+A1028 -> B16 | I1028: =IF(ISERROR(VLOOKUP(H1028,BD!BN$2:BO$51,2,FALSE)),"",VLOOKUP(H1028,BD!BN$2:BO$51,2,FALSE)) -> BLOQUE 16 | J1028: =IF(B1028="","",B1028) | K1028: =+C1028 -> DICARON | L1028: =+D1028 -> PAD | M1028: =+IF(F1028=F1027,E1028&RIGHT(G1028,2),E1028) -> DICARON-001 | N1028: Open Wells
A1029: B16 | C1029: GINTA | D1029: PAD | E1029: GINTA-001 | F1029: GNA-001 | G1029: GNA-001 | H1029: =+A1029 -> B16 | I1029: =IF(ISERROR(VLOOKUP(H1029,BD!BN$2:BO$51,2,FALSE)),"",VLOOKUP(H1029,BD!BN$2:BO$51,2,FALSE)) -> BLOQUE 16 | J1029: =IF(B1029="","",B1029) | K1029: =+C1029 -> GINTA | L1029: =+D1029 -> PAD | M1029: =+IF(F1029=F1028,E1029&RIGHT(G1029,2),E1029) -> GINTA-001 | N1029: Open Wells
A1030: B16 | C1030: ZAPARO | D1030: PAD | E1030: ZAPARO-001 | F1030: ZPR-001 | G1030: ZPR-001 | H1030: =+A1030 -> B16 | I1030: =IF(ISERROR(VLOOKUP(H1030,BD!BN$2:BO$51,2,FALSE)),"",VLOOKUP(H1030,BD!BN$2:BO$51,2,FALSE)) -> BLOQUE 16 | J1030: =IF(B1030="","",B1030) | K1030: =+C1030 -> ZAPARO | L1030: =+D1030 -> PAD | M1030: =+IF(F1030=F1029,E1030&RIGHT(G1030,2),E1030) -> ZAPARO-001 | N1030: Open Wells
A1031: B17 | C1031: AGUILA | D1031: PAD | E1031: AGUILA-001 | F1031: AGL-001 | G1031: AGL-001 | H1031: =+A1031 -> B17 | I1031: =IF(ISERROR(VLOOKUP(H1031,BD!BN$2:BO$51,2,FALSE)),"",VLOOKUP(H1031,BD!BN$2:BO$51,2,FALSE)) -> BLOQUE 17 | J1031: =IF(B1031="","",B1031) | K1031: =+C1031 -> AGUILA | L1031: =+D1031 -> PAD | M1031: =+IF(F1031=F1030,E1031&RIGHT(G1031,2),E1031) -> AGUILA-001 | N1031: Open Wells
A1032: B17 | C1032: BALATA | D1032: PAD | E1032: BALATA-001 | F1032: BLT-001 | G1032: BLT-001 | H1032: =+A1032 -> B17 | I1032: =IF(ISERROR(VLOOKUP(H1032,BD!BN$2:BO$51,2,FALSE)),"",VLOOKUP(H1032,BD!BN$2:BO$51,2,FALSE)) -> BLOQUE 17 | J1032: =IF(B1032="","",B1032) | K1032: =+C1032 -> BALATA | L1032: =+D1032 -> PAD | M1032: =+IF(F1032=F1031,E1032&RIGHT(G1032,2),E1032) -> BALATA-001 | N1032: Open Wells
A1033: B17 | C1033: CURARAY | D1033: PAD | E1033: CURARAY-001 | F1033: CRR-001 | G1033: CRR-001 | H1033: =+A1033 -> B17 | I1033: =IF(ISERROR(VLOOKUP(H1033,BD!BN$2:BO$51,2,FALSE)),"",VLOOKUP(H1033,BD!BN$2:BO$51,2,FALSE)) -> BLOQUE 17 | J1033: =IF(B1033="","",B1033) | K1033: =+C1033 -> CURARAY | L1033: =+D1033 -> PAD | M1033: =+IF(F1033=F1032,E1033&RIGHT(G1033,2),E1033) -> CURARAY-001 | N1033: Open Wells
A1034: B17 | C1034: ENTRE RIOS | D1034: PAD | E1034: ENTRE RIOS-001 | F1034: ENT-001 | G1034: ENT-001 | H1034: =+A1034 -> B17 | I1034: =IF(ISERROR(VLOOKUP(H1034,BD!BN$2:BO$51,2,FALSE)),"",VLOOKUP(H1034,BD!BN$2:BO$51,2,FALSE)) -> BLOQUE 17 | J1034: =IF(B1034="","",B1034) | K1034: =+C1034 -> ENTRE RIOS | L1034: =+D1034 -> PAD | M1034: =+IF(F1034=F1033,E1034&RIGHT(G1034,2),E1034) -> ENTRE RIOS-001 | N1034: Open Wells
... A1039: B17 | C1039: TIWAE | D1039: PAD | E1039: TIWAE-001 | F1039: TIW-001 | G1039: TIW-001 | H1039: =+A1039 -> B17 | I1039: =IF(ISERROR(VLOOKUP(H1039,BD!BN$2:BO$51,2,FALSE)),"",VLOOKUP(H1039,BD!BN$2:BO$51,2,FALSE)) -> BLOQUE 17 | J1039: =IF(B1039="","",B1039) | K1039: =+C1039 -> TIWAE | L1039: =+D1039 -> PAD | M1039: =+IF(F1039=F1038,E1039&RIGHT(G1039,2),E1039) -> TIWAE-001 | N1039: Open Wells
A1040: B18 | B1040: PA | C1040: BALSAYACU | D1040: PAD A | E1040: BALSAYACU-A001A | F1040: BLSA-001A | G1040: BLSA-001A | H1040: =+A1040 -> B18 | I1040: =IF(ISERROR(VLOOKUP(H1040,BD!BN$2:BO$51,2,FALSE)),"",VLOOKUP(H1040,BD!BN$2:BO$51,2,FALSE)) -> BLOQUE 18 | J1040: =IF(B1040="","",B1040) -> PA | K1040: =+C1040 -> BALSAYACU | L1040: =+D1040 -> PAD A | M1040: =+IF(F1040=F1039,E1040&RIGHT(G1040,2),E1040) -> BALSAYACU-A001A | N1040: Open Wells
A1041: B18 | B1041: PA | C1041: BALSAYACU | D1041: PAD A | E1041: BALSAYACU-A001 | F1041: BLSA-001 | G1041: BLSA-001 | H1041: =+A1041 -> B18 | I1041: =IF(ISERROR(VLOOKUP(H1041,BD!BN$2:BO$51,2,FALSE)),"",VLOOKUP(H1041,BD!BN$2:BO$51,2,FALSE)) -> BLOQUE 18 | J1041: =IF(B1041="","",B1041) -> PA | K1041: =+C1041 -> BALSAYACU | L1041: =+D1041 -> PAD A | M1041: =+IF(F1041=F1040,E1041&RIGHT(G1041,2),E1041) -> BALSAYACU-A001 | N1041: Open Wells
A1042: B18 | B1042: PA | C1042: CHONTAYACU | D1042: PAD A | E1042: CHONTAYACU-A001 | F1042: CHTA-001 | G1042: CHTA-001 | H1042: =+A1042 -> B18 | I1042: =IF(ISERROR(VLOOKUP(H1042,BD!BN$2:BO$51,2,FALSE)),"",VLOOKUP(H1042,BD!BN$2:BO$51,2,FALSE)) -> BLOQUE 18 | J1042: =IF(B1042="","",B1042) -> PA | K1042: =+C1042 -> CHONTAYACU | L1042: =+D1042 -> PAD A | M1042: =+IF(F1042=F1041,E1042&RIGHT(G1042,2),E1042) -> CHONTAYACU-A001 | N1042: Open Wells
...
